{"title":"Combined feed","url":"https://KPOPCORD.github.io/magazine/all.xml","elements":[{"title":"제38회 골든디스크어워즈 - 인기상 투표는 벅스에서! (벅스 ─ 뮤직포스트)","contents":"주간 핫이슈","link":"https://music.bugs.co.kr/musicpost/HKD9G5RNWWRG2HC62ABA?&wl_ref=list_sp_01_h","retrieved":1701317613303,"image":"https://image.bugsm.co.kr/uniContent/banner/HKD9G5RNWWRG2HC62ABA/title_mobile_306.jpg"},{"title":"Favorite - 당신의 최애는 누구인가요? (벅스 ─ 뮤직포스트)","contents":"주간 핫이슈","link":"https://music.bugs.co.kr/musicpost/TUOURXXUMYUZVM1VI8GW?&wl_ref=list_sp_01_h","retrieved":1701317613303,"image":"https://image.bugsm.co.kr/uniContent/banner/TUOURXXUMYUZVM1VI8GW/title_mobile_306.jpg"},{"title":"현오 - 솔로로 돌아온 [이별을 배웠어 (Always In My Heart)] 발매 기념 인터뷰 (벅스 ─ 뮤직포스트)","contents":"주간 핫이슈","link":"https://music.bugs.co.kr/musicpost/GRH682A3JFFFC686Z9HO?&wl_ref=list_sp_01_h","retrieved":1701076340977,"image":"https://image.bugsm.co.kr/uniContent/banner/GRH682A3JFFFC686Z9HO/title_mobile_306.jpg"},{"title":"모트(Motte) - 새 더블 싱글 [Night Waves] MV 촬영 현장 공개 (벅스 ─ 뮤직포스트)","contents":"주간 핫이슈","link":"https://music.bugs.co.kr/musicpost/FXE2MDLVO02M1CODRNIA?&wl_ref=list_sp_01_h","retrieved":1700471536235,"image":"https://image.bugsm.co.kr/uniContent/banner/FXE2MDLVO02M1CODRNIA/title_mobile_306.jpg"},{"title":"팝송으로 배우는 영어! 76.Johnny Orlando - 'someone will love you better' (벅스 ─ 뮤직포스트)","contents":"뮤직&amp;","link":"https://music.bugs.co.kr/musicpost/PHHTGRG260PXZ01QH1UU?&wl_ref=list_sp_01_h","retrieved":1700186030726},{"title":"뭘 들을까? - 2023년 11월 노래 모음! (벅스 ─ 뮤직포스트)","contents":"뮤직&amp;","link":"https://music.bugs.co.kr/musicpost/LE8ONPWBJW6YNTT7OYZI?&wl_ref=list_sp_01_h","retrieved":1700101491441},{"title":"I'll (아일) - 미니앨범 [Medlar Mixtape] 타이틀곡 'One More' M/V 촬영 현장 공개 (벅스 ─ 뮤직포스트)","contents":"주간 핫이슈","link":"https://music.bugs.co.kr/musicpost/9WLMS59IALQMHGQCTLKQ?&wl_ref=list_sp_01_h","retrieved":1700082612510,"image":"https://image.bugsm.co.kr/uniContent/banner/9WLMS59IALQMHGQCTLKQ/title_mobile_306.jpg"},{"title":"우예린 - 새 싱글 '토끼(tokki)' 앨범 커버 촬영기 공개 (벅스 ─ 뮤직포스트)","contents":"주간 핫이슈","link":"https://music.bugs.co.kr/musicpost/RBN3BP23K3D8EGRHPW5C?&wl_ref=list_sp_01_h","retrieved":1700082612498,"image":"https://image.bugsm.co.kr/uniContent/banner/RBN3BP23K3D8EGRHPW5C/title_mobile_306.jpg"},{"title":"김필(Kim Feel) - The 3rd mini album [LIFE] 자켓 촬영 비하인드 공개 (벅스 ─ 뮤직포스트)","contents":"주간 핫이슈","link":"https://music.bugs.co.kr/musicpost/6RF5EL9TH48HH4IV2M2M?&wl_ref=list_sp_01_h","retrieved":1700082612511,"image":"https://image.bugsm.co.kr/uniContent/banner/6RF5EL9TH48HH4IV2M2M/title_mobile_306.jpg"},{"title":"유다빈밴드 - 싱글 [ONCE] 'CALLING' 라이브 클립 촬영기 (벅스 ─ 뮤직포스트)","contents":"주간 핫이슈","link":"https://music.bugs.co.kr/musicpost/79ZYWWFF6V0DGQQEEJXJ?&wl_ref=list_sp_01_h","retrieved":1700082612511,"image":"https://image.bugsm.co.kr/uniContent/banner/79ZYWWFF6V0DGQQEEJXJ/title_mobile_306.jpg"},{"title":"팝송으로 배우는 영어! 75.Olivia Rodrigo - 'get him back!' (벅스 ─ 뮤직포스트)","contents":"뮤직&amp;","link":"https://music.bugs.co.kr/musicpost/3J2ME05AMNH6O42WAXMA?&wl_ref=list_sp_01_h","retrieved":1700082612512},{"title":"GHOST9(고스트나인) - [ARCADE : O] 자켓 촬영 현장 공개 (벅스 ─ 뮤직포스트)","contents":"주간 핫이슈","link":"https://music.bugs.co.kr/musicpost/UFHTM350EPQRZBTM2C0V?&wl_ref=list_sp_01_h","retrieved":1700082612512,"image":"https://image.bugsm.co.kr/uniContent/banner/UFHTM350EPQRZBTM2C0V/title_mobile_306.jpg"},{"title":"웨더보트 - 첫 번째 정규앨범 [Escape from the] MV 촬영 현장 공개 (벅스 ─ 뮤직포스트)","contents":"주간 핫이슈","link":"https://music.bugs.co.kr/musicpost/CBFHGGS0NN18LQ66A1XS?&wl_ref=list_sp_01_h","retrieved":1700082612512,"image":"https://image.bugsm.co.kr/uniContent/banner/CBFHGGS0NN18LQ66A1XS/title_mobile_306.jpg"},{"title":"CHERISH (체리쉬) - 새 싱글 [To.Youth] 앨범 작업 비하인드 공개 (벅스 ─ 뮤직포스트)","contents":"주간 핫이슈","link":"https://music.bugs.co.kr/musicpost/OP2X6LLHX3CA64SSYKWG?&wl_ref=list_sp_01_h","retrieved":1700082612516,"image":"https://image.bugsm.co.kr/uniContent/banner/OP2X6LLHX3CA64SSYKWG/title_mobile_306.jpg"},{"title":"뭘 들을까? - 2023년 10월 노래 모음! (벅스 ─ 뮤직포스트)","contents":"뮤직&amp;","link":"https://music.bugs.co.kr/musicpost/U1DF97NL7IY9SMNV24OR?&wl_ref=list_sp_01_h","retrieved":1700082612516},{"title":"터치드(TOUCHED) - [Yellow Supernova Remnant] 앨범 작업기 (벅스 ─ 뮤직포스트)","contents":"주간 핫이슈","link":"https://music.bugs.co.kr/musicpost/Z79LZBGHDDNK8TDRQHBX?&wl_ref=list_sp_01_h","retrieved":1700082612517,"image":"https://image.bugsm.co.kr/uniContent/banner/Z79LZBGHDDNK8TDRQHBX/title_mobile_306.jpg"},{"title":"팝송으로 배우는 영어! 74.LANY - 'XXL' (벅스 ─ 뮤직포스트)","contents":"뮤직&amp;","link":"https://music.bugs.co.kr/musicpost/PPFJ9MKTEN3UM17MP2VC?&wl_ref=list_sp_01_h","retrieved":1700082612518},{"title":"안신애 - 내추럴하고 솔직한 모습을 담아낸 자켓 촬영 현장 (벅스 ─ 뮤직포스트)","contents":"주간 핫이슈","link":"https://music.bugs.co.kr/musicpost/PXO0O2TTY74SRWEASQDV?&wl_ref=list_sp_01_h","retrieved":1700082612519,"image":"https://image.bugsm.co.kr/uniContent/banner/PXO0O2TTY74SRWEASQDV/title_mobile_306.jpg"},{"title":"유주(YUJU) - '따라랏' MV/자켓 촬영 현장 (벅스 ─ 뮤직포스트)","contents":"주간 핫이슈","link":"https://music.bugs.co.kr/musicpost/J6YNB1KCCMJIW8JAALHD?&wl_ref=list_sp_01_h","retrieved":1700082612520,"image":"https://image.bugsm.co.kr/uniContent/banner/J6YNB1KCCMJIW8JAALHD/title_mobile_306.jpg"},{"title":"뭘 들을까? - 2023년 9월 노래 모음! (벅스 ─ 뮤직포스트)","contents":"뮤직&amp;","link":"https://music.bugs.co.kr/musicpost/MNTDJLZ338YIU8V7E9RB?&wl_ref=list_sp_01_h","retrieved":1700082612522},{"title":"Loossemble (루셈블) - 새로운 서사의 시작인 첫 데뷔 앨범 재킷 촬영 현장 (벅스 ─ 뮤직포스트)","contents":"주간 핫이슈","link":"https://music.bugs.co.kr/musicpost/7CDVAPS5Z3T1I79DD0XH?&wl_ref=list_sp_01_h","retrieved":1700082612524,"image":"https://image.bugsm.co.kr/uniContent/banner/7CDVAPS5Z3T1I79DD0XH/title_mobile_306.jpg"},{"title":"CHERISH (체리쉬) - 데뷔 싱글! 'Can't you see me?' LIVE 촬영기 공개 (벅스 ─ 뮤직포스트)","contents":"주간 핫이슈","link":"https://music.bugs.co.kr/musicpost/BVAXCZHESZVGI78E8ZWS?&wl_ref=list_sp_01_h","retrieved":1700082612525,"image":"https://image.bugsm.co.kr/uniContent/banner/BVAXCZHESZVGI78E8ZWS/title_mobile_306.jpg"},{"title":"Leo (리오) - 새 싱글 앨범 [IZAKAYA] 발매 기념 인터뷰 (벅스 ─ 뮤직포스트)","contents":"주간 핫이슈","link":"https://music.bugs.co.kr/musicpost/8WIAGMYEG7I056WYJ0TB?&wl_ref=list_sp_01_h","retrieved":1700082612527,"image":"https://image.bugsm.co.kr/uniContent/banner/8WIAGMYEG7I056WYJ0TB/title_mobile_306.jpg"},{"title":"TRENDZ (트렌드지) - The 3rd Single Album [STILL ON MY WAY] 자켓 촬영 비하인드 공개! (벅스 ─ 뮤직포스트)","contents":"주간 핫이슈","link":"https://music.bugs.co.kr/musicpost/XXSM7IXSM0R6LFEL9XRD?&wl_ref=list_sp_01_h","retrieved":1700082612528,"image":"https://image.bugsm.co.kr/uniContent/banner/XXSM7IXSM0R6LFEL9XRD/title_mobile_306.jpg"},{"title":"듣기만 해도 용기백배! 수능을 마친 여러분에게 바치는 클래식 (지니 ─ 매거진)","contents":"클래식 공감","link":"https://genie.co.kr/magazine/subMain?ctid=8&mgz_seq=13824&pg=1","retrieved":1701313912233,"image":"https://image.genie.co.kr/Y/IMAGE/IMG_MUZICAT/IV2/Genie_Magazine/13824/Mgz_Main_List_20231130113908.jpg/dims/resize/Q_80,0"},{"title":"리하 (LIHA)의 [그땐 몰랐었지 (웹드라마 '청춘유랑단' OST)] 발매 ... (지니 ─ 매거진)","contents":"스페셜","link":"https://genie.co.kr/magazine/subMain?ctid=1&mgz_seq=13821&pg=1","retrieved":1701313912234,"image":"https://image.genie.co.kr/Y/IMAGE/IMG_MUZICAT/IV2/Genie_Magazine/13821/Mgz_Main_List_20231130091252.jpg/dims/resize/Q_80,0"},{"title":"1년만에 디지털 싱글 “RollerCoaster”로 돌아온 SAAY (쎄이),... (지니 ─ 매거진)","contents":"스페셜","link":"https://genie.co.kr/magazine/subMain?ctid=1&mgz_seq=13820&pg=1","retrieved":1701252749477,"image":"https://image.genie.co.kr/Y/IMAGE/IMG_MUZICAT/IV2/Genie_Magazine/13820/Mgz_Main_List_20231129174016.jpg/dims/resize/Q_80,0"},{"title":"[곁 (웹툰 '막내 황녀님' X 설아 (우주소녀))] 발매 기념 인터뷰! (지니 ─ 매거진)","contents":"스페셜","link":"https://genie.co.kr/magazine/subMain?ctid=1&mgz_seq=13819&pg=1","retrieved":1701252749487,"image":"https://image.genie.co.kr/Y/IMAGE/IMG_MUZICAT/IV2/Genie_Magazine/13819/Mgz_Main_List_20231129163508.jpg/dims/resize/Q_80,0"},{"title":"＃1년차정신과의사 ＃17년차선미덕후 ＃24시간이_모자라 '벤죠디' 편 (지니 ─ 매거진)","contents":"#왓_인_플","link":"https://genie.co.kr/magazine/subMain?ctid=40&mgz_seq=13816&pg=1","retrieved":1701252749488,"image":"https://image.genie.co.kr/Y/IMAGE/IMG_MUZICAT/IV2/Genie_Magazine/13816/Mgz_Main_List_20231129170258.jpg/dims/resize/Q_80,0"},{"title":"새로운 시작을 향해 노래하는 ‘연경이’에게 듣는 네 번째 싱글 [My Endi... (지니 ─ 매거진)","contents":"스페셜","link":"https://genie.co.kr/magazine/subMain?ctid=1&mgz_seq=13818&pg=1","retrieved":1701227520959,"image":"https://image.genie.co.kr/Y/IMAGE/IMG_MUZICAT/IV2/Genie_Magazine/13817/Mgz_Main_List_20231129092621.jpg/dims/resize/Q_80,0"},{"title":"브리티시 포크 록 레전드 ‘Matt Deighton(맷 데이튼)’의 컴백 스토... (지니 ─ 매거진)","contents":"스페셜","link":"https://genie.co.kr/magazine/subMain?ctid=1&mgz_seq=13817&pg=1","retrieved":1701227520960,"image":"https://image.genie.co.kr/Y/IMAGE/IMG_MUZICAT/IV2/Genie_Magazine/13817/Mgz_Main_List_20231129115741.jpg/dims/resize/Q_80,0"},{"title":"새로운 마법의 세계로 와요~ 뮤지컬 배우 박강현의 'MAGIC' MV 제작기 (지니 ─ 매거진)","contents":"스페셜","link":"https://genie.co.kr/magazine/subMain?ctid=1&mgz_seq=13814&pg=1","retrieved":1701162729587,"image":"https://image.genie.co.kr/Y/IMAGE/IMG_MUZICAT/IV2/Genie_Magazine/13814/Mgz_Main_List_20231128161905.jpg/dims/resize/Q_80,0"},{"title":"New Release #170 : \n김창완, 비욕&로살리아 (VIBE ─ 매거진)","contents":"<span data-v-67bd4c1e=\"\" class=\"blind\">작성일</span> 2023.11.27","link":"https://vibe.naver.com/magazines/62415","retrieved":1701141152427,"image":"https://music-phinf.pstatic.net/20231127_189/1701063224878HMJOn_JPEG/%C4%BF%B9%F61.jpg?type=w720"},{"title":"컴백한 빅스의 \n기억상실? (VIBE ─ 매거진)","contents":"<span data-v-67bd4c1e=\"\" class=\"blind\">작성일</span> 2023.11.22","link":"https://vibe.naver.com/magazines/62414","retrieved":1701065743105,"image":"https://music-phinf.pstatic.net/20231122_197/1700615132395P5HRB_JPEG/%C4%BF%B9%F61.jpg?type=w720"},{"title":"이주의 디깅 #171 \n딘 (VIBE ─ 매거진)","contents":"<span data-v-67bd4c1e=\"\" class=\"blind\">작성일</span> 2023.11.21","link":"https://vibe.naver.com/magazines/62413","retrieved":1700637127515,"image":"https://music-phinf.pstatic.net/20231121_20/1700550858823OK6zo_JPEG/%C4%BF%B9%F61.jpg?type=w720"},{"title":"New Releases #169 : \n레드벨벳, 테이트 맥레이 (VIBE ─ 매거진)","contents":"<span data-v-67bd4c1e=\"\" class=\"blind\">작성일</span> 2023.11.20","link":"https://vibe.naver.com/magazines/62412","retrieved":1700554570690,"image":"data:image/png;base64,iVBORw0KGgoAAAANSUhEUgAAAZAAAAGQAQMAAAC6caSPAAAABGdBTUEAALGPC/xhBQAAAAFzUkdCAK7OHOkAAAAGUExURRoaGhERETZTak8AAAIlSURBVHja7doxbsIwGMVx0wyR2iHcIEfxUTgKPhpbV47gsWOGDgwINzgqOCQo339oFbUvQweLH++TIQnQ59Kzwz09RERERERERERERER+l9SYvKUASbVPMOWlX4ApowUT2Sea4hNN2Q0LIKV+XLATpShldSkXj1MCJsF5ONihP5tZytFR8pGvGWSwz+EyQ1IiJ53Dg0UNpsE02B8ZbIsHqxMerGX3lzh8IgtssE3CKRW6i/n3ONwwzCn9SP1gDUnpnz8OxJzS5pSWpPic4knKPqd4kpJwyvU17IaP41ZSDSmUwJT6lnIhpGOkuaWcIek3+cRJR8jh+52GSJP/2knIGxfIJofrK3pxhOSHnRx4w+Tnfw2EnOE38U25u+azMlLii921XpRO+oVERERERERERERE5J8R7YuIiIiIiIiIiIjIWkiNyb2+ZyVFfc9IyvqekZQrNnL9Tx5L8Ymm7IYVkPJYrQJEKUpZXcq9vmcmAZOivmckh6L2YiNHR8m4vmchD/U9C4mcPBSFfihFg2kwDbbKwbZ4sKK+Z01p2f0lulF9zzjYJuGUCt3FJvW9RTKt7y2SaX1vkbQ5pSUpflKsWyT7nOJJSsIpM/W9JTJT37MQmDJT37OQjpEmTep7RuKL+p6ddIQcxvU9I2mK+p6FhHF9z7LJYVzfs5D8OHPfca6+ZyBn+E18pr5nOCsjJdP63vJF6aRfSERERERERERERERE8vEF75usLCqqK/sAAAAASUVORK5CYII="},{"title":"엔하이픈, \n오렌지빛 따뜻한 사랑 (VIBE ─ 매거진)","contents":"<span data-v-67bd4c1e=\"\" class=\"blind\">작성일</span> 2023.11.16","link":"https://vibe.naver.com/magazines/62411","retrieved":1700460918105,"image":"data:image/png;base64,iVBORw0KGgoAAAANSUhEUgAAAZAAAAGQAQMAAAC6caSPAAAABGdBTUEAALGPC/xhBQAAAAFzUkdCAK7OHOkAAAAGUExURRoaGhERETZTak8AAAIlSURBVHja7doxbsIwGMVx0wyR2iHcIEfxUTgKPhpbV47gsWOGDgwINzgqOCQo339oFbUvQweLH++TIQnQ59Kzwz09RERERERERERERER+l9SYvKUASbVPMOWlX4ApowUT2Sea4hNN2Q0LIKV+XLATpShldSkXj1MCJsF5ONihP5tZytFR8pGvGWSwz+EyQ1IiJ53Dg0UNpsE02B8ZbIsHqxMerGX3lzh8IgtssE3CKRW6i/n3ONwwzCn9SP1gDUnpnz8OxJzS5pSWpPic4knKPqd4kpJwyvU17IaP41ZSDSmUwJT6lnIhpGOkuaWcIek3+cRJR8jh+52GSJP/2knIGxfIJofrK3pxhOSHnRx4w+Tnfw2EnOE38U25u+azMlLii921XpRO+oVERERERERERERE5J8R7YuIiIiIiIiIiIjIWkiNyb2+ZyVFfc9IyvqekZQrNnL9Tx5L8Ymm7IYVkPJYrQJEKUpZXcq9vmcmAZOivmckh6L2YiNHR8m4vmchD/U9C4mcPBSFfihFg2kwDbbKwbZ4sKK+Z01p2f0lulF9zzjYJuGUCt3FJvW9RTKt7y2SaX1vkbQ5pSUpflKsWyT7nOJJSsIpM/W9JTJT37MQmDJT37OQjpEmTep7RuKL+p6ddIQcxvU9I2mK+p6FhHF9z7LJYVzfs5D8OHPfca6+ZyBn+E18pr5nOCsjJdP63vJF6aRfSERERERERERERERE8vEF75usLCqqK/sAAAAASUVORK5CYII="},{"title":"New Releases #168 : \n에스파, 두아리파 (VIBE ─ 매거진)","contents":"<span data-v-67bd4c1e=\"\" class=\"blind\">작성일</span> 2023.11.13","link":"https://vibe.naver.com/magazines/62410","retrieved":1700201709411,"image":"data:image/png;base64,iVBORw0KGgoAAAANSUhEUgAAAZAAAAGQAQMAAAC6caSPAAAABGdBTUEAALGPC/xhBQAAAAFzUkdCAK7OHOkAAAAGUExURRoaGhERETZTak8AAAIlSURBVHja7doxbsIwGMVx0wyR2iHcIEfxUTgKPhpbV47gsWOGDgwINzgqOCQo339oFbUvQweLH++TIQnQ59Kzwz09RERERERERERERER+l9SYvKUASbVPMOWlX4ApowUT2Sea4hNN2Q0LIKV+XLATpShldSkXj1MCJsF5ONihP5tZytFR8pGvGWSwz+EyQ1IiJ53Dg0UNpsE02B8ZbIsHqxMerGX3lzh8IgtssE3CKRW6i/n3ONwwzCn9SP1gDUnpnz8OxJzS5pSWpPic4knKPqd4kpJwyvU17IaP41ZSDSmUwJT6lnIhpGOkuaWcIek3+cRJR8jh+52GSJP/2knIGxfIJofrK3pxhOSHnRx4w+Tnfw2EnOE38U25u+azMlLii921XpRO+oVERERERERERERE5J8R7YuIiIiIiIiIiIjIWkiNyb2+ZyVFfc9IyvqekZQrNnL9Tx5L8Ymm7IYVkPJYrQJEKUpZXcq9vmcmAZOivmckh6L2YiNHR8m4vmchD/U9C4mcPBSFfihFg2kwDbbKwbZ4sKK+Z01p2f0lulF9zzjYJuGUCt3FJvW9RTKt7y2SaX1vkbQ5pSUpflKsWyT7nOJJSsIpM/W9JTJT37MQmDJT37OQjpEmTep7RuKL+p6ddIQcxvU9I2mK+p6FhHF9z7LJYVzfs5D8OHPfca6+ZyBn+E18pr5nOCsjJdP63vJF6aRfSERERERERERERERE8vEF75usLCqqK/sAAAAASUVORK5CYII="},{"title":"이주의 디깅 #170 \n바밍 타이거 (VIBE ─ 매거진)","contents":"<span data-v-67bd4c1e=\"\" class=\"blind\">작성일</span> 2023.11.07","link":"https://vibe.naver.com/magazines/62409","retrieved":1699859478030,"image":"data:image/png;base64,iVBORw0KGgoAAAANSUhEUgAAAZAAAAGQAQMAAAC6caSPAAAABGdBTUEAALGPC/xhBQAAAAFzUkdCAK7OHOkAAAAGUExURRoaGhERETZTak8AAAIlSURBVHja7doxbsIwGMVx0wyR2iHcIEfxUTgKPhpbV47gsWOGDgwINzgqOCQo339oFbUvQweLH++TIQnQ59Kzwz09RERERERERERERER+l9SYvKUASbVPMOWlX4ApowUT2Sea4hNN2Q0LIKV+XLATpShldSkXj1MCJsF5ONihP5tZytFR8pGvGWSwz+EyQ1IiJ53Dg0UNpsE02B8ZbIsHqxMerGX3lzh8IgtssE3CKRW6i/n3ONwwzCn9SP1gDUnpnz8OxJzS5pSWpPic4knKPqd4kpJwyvU17IaP41ZSDSmUwJT6lnIhpGOkuaWcIek3+cRJR8jh+52GSJP/2knIGxfIJofrK3pxhOSHnRx4w+Tnfw2EnOE38U25u+azMlLii921XpRO+oVERERERERERERE5J8R7YuIiIiIiIiIiIjIWkiNyb2+ZyVFfc9IyvqekZQrNnL9Tx5L8Ymm7IYVkPJYrQJEKUpZXcq9vmcmAZOivmckh6L2YiNHR8m4vmchD/U9C4mcPBSFfihFg2kwDbbKwbZ4sKK+Z01p2f0lulF9zzjYJuGUCt3FJvW9RTKt7y2SaX1vkbQ5pSUpflKsWyT7nOJJSsIpM/W9JTJT37MQmDJT37OQjpEmTep7RuKL+p6ddIQcxvU9I2mK+p6FhHF9z7LJYVzfs5D8OHPfca6+ZyBn+E18pr5nOCsjJdP63vJF6aRfSERERERERERERERE8vEF75usLCqqK/sAAAAASUVORK5CYII="},{"title":"New Releases #167 : \n 정국, 비틀스 (VIBE ─ 매거진)","contents":"<span data-v-67bd4c1e=\"\" class=\"blind\">작성일</span> 2023.11.06","link":"https://vibe.naver.com/magazines/62408","retrieved":1699330428473,"image":"data:image/png;base64,iVBORw0KGgoAAAANSUhEUgAAAZAAAAGQAQMAAAC6caSPAAAABGdBTUEAALGPC/xhBQAAAAFzUkdCAK7OHOkAAAAGUExURRoaGhERETZTak8AAAIlSURBVHja7doxbsIwGMVx0wyR2iHcIEfxUTgKPhpbV47gsWOGDgwINzgqOCQo339oFbUvQweLH++TIQnQ59Kzwz09RERERERERERERER+l9SYvKUASbVPMOWlX4ApowUT2Sea4hNN2Q0LIKV+XLATpShldSkXj1MCJsF5ONihP5tZytFR8pGvGWSwz+EyQ1IiJ53Dg0UNpsE02B8ZbIsHqxMerGX3lzh8IgtssE3CKRW6i/n3ONwwzCn9SP1gDUnpnz8OxJzS5pSWpPic4knKPqd4kpJwyvU17IaP41ZSDSmUwJT6lnIhpGOkuaWcIek3+cRJR8jh+52GSJP/2knIGxfIJofrK3pxhOSHnRx4w+Tnfw2EnOE38U25u+azMlLii921XpRO+oVERERERERERERE5J8R7YuIiIiIiIiIiIjIWkiNyb2+ZyVFfc9IyvqekZQrNnL9Tx5L8Ymm7IYVkPJYrQJEKUpZXcq9vmcmAZOivmckh6L2YiNHR8m4vmchD/U9C4mcPBSFfihFg2kwDbbKwbZ4sKK+Z01p2f0lulF9zzjYJuGUCt3FJvW9RTKt7y2SaX1vkbQ5pSUpflKsWyT7nOJJSsIpM/W9JTJT37MQmDJT37OQjpEmTep7RuKL+p6ddIQcxvU9I2mK+p6FhHF9z7LJYVzfs5D8OHPfca6+ZyBn+E18pr5nOCsjJdP63vJF6aRfSERERERERERERERE8vEF75usLCqqK/sAAAAASUVORK5CYII="},{"title":"WayV의 \n의미있는 성장 (VIBE ─ 매거진)","contents":"<span data-v-67bd4c1e=\"\" class=\"blind\">작성일</span> 2023.11.03","link":"https://vibe.naver.com/magazines/62407","retrieved":1699254655702,"image":"data:image/png;base64,iVBORw0KGgoAAAANSUhEUgAAAZAAAAGQAQMAAAC6caSPAAAABGdBTUEAALGPC/xhBQAAAAFzUkdCAK7OHOkAAAAGUExURRoaGhERETZTak8AAAIlSURBVHja7doxbsIwGMVx0wyR2iHcIEfxUTgKPhpbV47gsWOGDgwINzgqOCQo339oFbUvQweLH++TIQnQ59Kzwz09RERERERERERERER+l9SYvKUASbVPMOWlX4ApowUT2Sea4hNN2Q0LIKV+XLATpShldSkXj1MCJsF5ONihP5tZytFR8pGvGWSwz+EyQ1IiJ53Dg0UNpsE02B8ZbIsHqxMerGX3lzh8IgtssE3CKRW6i/n3ONwwzCn9SP1gDUnpnz8OxJzS5pSWpPic4knKPqd4kpJwyvU17IaP41ZSDSmUwJT6lnIhpGOkuaWcIek3+cRJR8jh+52GSJP/2knIGxfIJofrK3pxhOSHnRx4w+Tnfw2EnOE38U25u+azMlLii921XpRO+oVERERERERERERE5J8R7YuIiIiIiIiIiIjIWkiNyb2+ZyVFfc9IyvqekZQrNnL9Tx5L8Ymm7IYVkPJYrQJEKUpZXcq9vmcmAZOivmckh6L2YiNHR8m4vmchD/U9C4mcPBSFfihFg2kwDbbKwbZ4sKK+Z01p2f0lulF9zzjYJuGUCt3FJvW9RTKt7y2SaX1vkbQ5pSUpflKsWyT7nOJJSsIpM/W9JTJT37MQmDJT37OQjpEmTep7RuKL+p6ddIQcxvU9I2mK+p6FhHF9z7LJYVzfs5D8OHPfca6+ZyBn+E18pr5nOCsjJdP63vJF6aRfSERERERERERERERE8vEF75usLCqqK/sAAAAASUVORK5CYII="},{"title":"다시 엔진을 켜는, \n위클리 (VIBE ─ 매거진)","contents":"<span data-v-67bd4c1e=\"\" class=\"blind\">작성일</span> 2023.11.01","link":"https://vibe.naver.com/magazines/62406","retrieved":1699002740924,"image":"data:image/png;base64,iVBORw0KGgoAAAANSUhEUgAAAZAAAAGQAQMAAAC6caSPAAAABGdBTUEAALGPC/xhBQAAAAFzUkdCAK7OHOkAAAAGUExURRoaGhERETZTak8AAAIlSURBVHja7doxbsIwGMVx0wyR2iHcIEfxUTgKPhpbV47gsWOGDgwINzgqOCQo339oFbUvQweLH++TIQnQ59Kzwz09RERERERERERERER+l9SYvKUASbVPMOWlX4ApowUT2Sea4hNN2Q0LIKV+XLATpShldSkXj1MCJsF5ONihP5tZytFR8pGvGWSwz+EyQ1IiJ53Dg0UNpsE02B8ZbIsHqxMerGX3lzh8IgtssE3CKRW6i/n3ONwwzCn9SP1gDUnpnz8OxJzS5pSWpPic4knKPqd4kpJwyvU17IaP41ZSDSmUwJT6lnIhpGOkuaWcIek3+cRJR8jh+52GSJP/2knIGxfIJofrK3pxhOSHnRx4w+Tnfw2EnOE38U25u+azMlLii921XpRO+oVERERERERERERE5J8R7YuIiIiIiIiIiIjIWkiNyb2+ZyVFfc9IyvqekZQrNnL9Tx5L8Ymm7IYVkPJYrQJEKUpZXcq9vmcmAZOivmckh6L2YiNHR8m4vmchD/U9C4mcPBSFfihFg2kwDbbKwbZ4sKK+Z01p2f0lulF9zzjYJuGUCt3FJvW9RTKt7y2SaX1vkbQ5pSUpflKsWyT7nOJJSsIpM/W9JTJT37MQmDJT37OQjpEmTep7RuKL+p6ddIQcxvU9I2mK+p6FhHF9z7LJYVzfs5D8OHPfca6+ZyBn+E18pr5nOCsjJdP63vJF6aRfSERERERERERERERE8vEF75usLCqqK/sAAAAASUVORK5CYII="},{"title":"New Release #166 : \n 세븐틴, 테일러 스위프트 (VIBE ─ 매거진)","contents":"<span data-v-67bd4c1e=\"\" class=\"blind\">작성일</span> 2023.10.30","link":"https://vibe.naver.com/magazines/62400","retrieved":1698829912340,"image":"data:image/png;base64,iVBORw0KGgoAAAANSUhEUgAAAZAAAAGQAQMAAAC6caSPAAAABGdBTUEAALGPC/xhBQAAAAFzUkdCAK7OHOkAAAAGUExURRoaGhERETZTak8AAAIlSURBVHja7doxbsIwGMVx0wyR2iHcIEfxUTgKPhpbV47gsWOGDgwINzgqOCQo339oFbUvQweLH++TIQnQ59Kzwz09RERERERERERERER+l9SYvKUASbVPMOWlX4ApowUT2Sea4hNN2Q0LIKV+XLATpShldSkXj1MCJsF5ONihP5tZytFR8pGvGWSwz+EyQ1IiJ53Dg0UNpsE02B8ZbIsHqxMerGX3lzh8IgtssE3CKRW6i/n3ONwwzCn9SP1gDUnpnz8OxJzS5pSWpPic4knKPqd4kpJwyvU17IaP41ZSDSmUwJT6lnIhpGOkuaWcIek3+cRJR8jh+52GSJP/2knIGxfIJofrK3pxhOSHnRx4w+Tnfw2EnOE38U25u+azMlLii921XpRO+oVERERERERERERE5J8R7YuIiIiIiIiIiIjIWkiNyb2+ZyVFfc9IyvqekZQrNnL9Tx5L8Ymm7IYVkPJYrQJEKUpZXcq9vmcmAZOivmckh6L2YiNHR8m4vmchD/U9C4mcPBSFfihFg2kwDbbKwbZ4sKK+Z01p2f0lulF9zzjYJuGUCt3FJvW9RTKt7y2SaX1vkbQ5pSUpflKsWyT7nOJJSsIpM/W9JTJT37MQmDJT37OQjpEmTep7RuKL+p6ddIQcxvU9I2mK+p6FhHF9z7LJYVzfs5D8OHPfca6+ZyBn+E18pr5nOCsjJdP63vJF6aRfSERERERERERERERE8vEF75usLCqqK/sAAAAASUVORK5CYII="},{"title":"올드 드레이크가 이런 건가요? : \n 시저, 제이 콜, 이트 (VIBE ─ 매거진)","contents":"<span data-v-67bd4c1e=\"\" class=\"blind\">작성일</span> 2023.10.26","link":"https://vibe.naver.com/magazines/62399","retrieved":1698653674223,"image":"data:image/png;base64,iVBORw0KGgoAAAANSUhEUgAAAZAAAAGQAQMAAAC6caSPAAAABGdBTUEAALGPC/xhBQAAAAFzUkdCAK7OHOkAAAAGUExURRoaGhERETZTak8AAAIlSURBVHja7doxbsIwGMVx0wyR2iHcIEfxUTgKPhpbV47gsWOGDgwINzgqOCQo339oFbUvQweLH++TIQnQ59Kzwz09RERERERERERERER+l9SYvKUASbVPMOWlX4ApowUT2Sea4hNN2Q0LIKV+XLATpShldSkXj1MCJsF5ONihP5tZytFR8pGvGWSwz+EyQ1IiJ53Dg0UNpsE02B8ZbIsHqxMerGX3lzh8IgtssE3CKRW6i/n3ONwwzCn9SP1gDUnpnz8OxJzS5pSWpPic4knKPqd4kpJwyvU17IaP41ZSDSmUwJT6lnIhpGOkuaWcIek3+cRJR8jh+52GSJP/2knIGxfIJofrK3pxhOSHnRx4w+Tnfw2EnOE38U25u+azMlLii921XpRO+oVERERERERERERE5J8R7YuIiIiIiIiIiIjIWkiNyb2+ZyVFfc9IyvqekZQrNnL9Tx5L8Ymm7IYVkPJYrQJEKUpZXcq9vmcmAZOivmckh6L2YiNHR8m4vmchD/U9C4mcPBSFfihFg2kwDbbKwbZ4sKK+Z01p2f0lulF9zzjYJuGUCt3FJvW9RTKt7y2SaX1vkbQ5pSUpflKsWyT7nOJJSsIpM/W9JTJT37MQmDJT37OQjpEmTep7RuKL+p6ddIQcxvU9I2mK+p6FhHF9z7LJYVzfs5D8OHPfca6+ZyBn+E18pr5nOCsjJdP63vJF6aRfSERERERERERERERE8vEF75usLCqqK/sAAAAASUVORK5CYII="},{"title":"연말에는 이 앨범 - \n크러쉬, 폴 블랑코, pH-1 (VIBE ─ 매거진)","contents":"아직 2023년의 마지막이 한 달 이상 남은 시점이지만, 이미 거리에서는 연말 분위기가 물씬 풍겨져 나오고 있다. 연말을 기념하기 위함일까? 수많은 뮤지션이 앨범을 발표하며 음악팬들의 귀와 마음을 즐겁게 만들어주고 있다. 이 중에서도 많은 장르 팬이 꼭 체크했으면 하는 몇 장의 앨범을 소개하고자 한다. – 힙합엘이","retrieved":1701328280653,"image":"https://music-phinf.pstatic.net/20231128_170/17011333664093aVpM_GIF/%C4%BF%B9%F61.gif?type=w840"},{"title":"지붕의 재발견 (현대카드 DIVE ─ POST)","contents":"사람과 자연을 연결하는 지붕 건축 프로젝트 4","link":"javascript:;","retrieved":1691583793600,"image":"https://dive.hyundaicard.com/resources/images/upload/content/9623d464e45f4fc68ed3bd7a4bb1b3a8.jpg"},{"title":"너 휴먼 그레이드야? (현대카드 DIVE ─ POST)","contents":"요즘 대세! 반려동물 프리미엄 사료 4","link":"javascript:;","retrieved":1691583793600,"image":"https://dive.hyundaicard.com/resources/images/upload/content/2b7138bc1ef44ab48dc38499bcd81435.jpg"},{"title":"구원찬의 특별한 에필로그 (현대카드 DIVE ─ POST)","contents":"진심을 노래하는 구원찬 ‘보너스 트랙’ 현장","link":"javascript:;","retrieved":1691583793600,"image":"https://dive.hyundaicard.com/resources/images/upload/content/88d2463231c845a4bc41a0a7fe325dc6.jpg"},{"title":"마쓰야마로소이다 (현대카드 DIVE ─ POST)","contents":"나쓰메 소세키가 사랑한 도시","link":"javascript:;","retrieved":1691583793600,"image":"https://dive.hyundaicard.com/resources/images/upload/content/9bc8e5b757e34e3cb51f3c1b8702b21e.jpg"},{"title":"The Last Beatles Song (현대카드 DIVE ─ POST)","contents":"비틀즈의 마지막 신곡을 만날 기회","link":"javascript:;","retrieved":1691583793600,"image":"https://dive.hyundaicard.com/resources/images/upload/content/77da8ab454204df8ae1e95dd1ab65981.jpg"},{"title":"리추얼을 선물할래 (현대카드 DIVE ─ POST)","contents":"센스 있는 연말 선물을 고민하고 있다면","link":"javascript:;","retrieved":1691583793600,"image":"https://dive.hyundaicard.com/resources/images/upload/content/7e3365f471774059b7e2e19478ae12ca.jpg"},{"title":"영감의 현장에서 (현대카드 DIVE ─ POST)","contents":"2023 현대카드 다빈치모텔 후기 #2","link":"javascript:;","retrieved":1691583793600,"image":"https://dive.hyundaicard.com/resources/images/upload/content/fa9acf4cfa6944718eda596178d3e195.jpg"},{"title":"붕세권이 아니라면 (현대카드 DIVE ─ POST)","contents":"집에서 구워도 맛있는 붕어빵 4","link":"javascript:;","retrieved":1691583793600,"image":"https://dive.hyundaicard.com/resources/images/upload/content/73a13f163a394fc89a5ac83373c30c6f.jpg"},{"title":"음악을 위한 공간 (현대카드 DIVE ─ POST)","contents":"음질에 취한다, 음악 감상실","link":"javascript:;","retrieved":1691583793600,"image":"https://dive.hyundaicard.com/resources/images/upload/content/6ffd245edfcf4cc68d76f32cef3059ae.jpg"}]}