{"title":"Combined feed","url":"https://KPOPCORD.github.io/magazine/all.xml","elements":[{"title":"팝송으로 배우는 영어! 73.Post Malone - 'Enough Is Enough' (벅스 ─ 뮤직포스트)","contents":"뮤직&amp;","link":"https://music.bugs.co.kr/musicpost/2LK714OHLMFE1FBTFTUA?&wl_ref=list_sp_01_h","retrieved":1693203265366},{"title":"SECRET NUMBER(시크릿넘버) - 7th Single [STARLIGHT] 촬영 비하인드 공개 (벅스 ─ 뮤직포스트)","contents":"주간 핫이슈","link":"https://music.bugs.co.kr/musicpost/Z8QHQRA4RBTP2QUWRWNT?&wl_ref=list_sp_01_h","retrieved":1692846665233,"image":"https://image.bugsm.co.kr/uniContent/banner/Z8QHQRA4RBTP2QUWRWNT/title_mobile_306.jpg"},{"title":"예린 (YERIN) - The 2nd Mini Album [Ready, Set, LOVE] 자켓/MV 촬영 비하인드 공개! (벅스 ─ 뮤직포스트)","contents":"주간 핫이슈","link":"https://music.bugs.co.kr/musicpost/L05VL47XR3JMRZ9DI5GX?&wl_ref=list_sp_01_h","retrieved":1692781839845,"image":"https://image.bugsm.co.kr/uniContent/banner/L05VL47XR3JMRZ9DI5GX/title_mobile_306.jpg"},{"title":"티아이오티 (TIOT) - 프리 데뷔 타이틀 '백전무패' 뮤직비디오 촬영 현장 (벅스 ─ 뮤직포스트)","contents":"주간 핫이슈","link":"https://music.bugs.co.kr/musicpost/0B85E58B0Z0N7T8EGD9Z?&wl_ref=list_sp_01_h","retrieved":1692781839846,"image":"https://image.bugsm.co.kr/uniContent/banner/0B85E58B0Z0N7T8EGD9Z/title_mobile_306.jpg"},{"title":"뭘 들을까? - 2023년 8월 노래 모음! (벅스 ─ 뮤직포스트)","contents":"뮤직&amp;","link":"https://music.bugs.co.kr/musicpost/A2LVLBM0BBCW1HHI3TSZ?&wl_ref=list_sp_01_h","retrieved":1692584129133},{"title":"우예린 - 새 싱글 'let it go! (daisy)' MV 촬영기 공개 (벅스 ─ 뮤직포스트)","contents":"주간 핫이슈","link":"https://music.bugs.co.kr/musicpost/PBF7UNR45NR51VNN24LZ?&wl_ref=list_sp_01_h","retrieved":1691615402588,"image":"https://image.bugsm.co.kr/uniContent/banner/PBF7UNR45NR51VNN24LZ/title_mobile_306.jpg"},{"title":"키썸(Kisum) - '냅두세요 (feat. 보이비)' 녹음 현장 공개! (벅스 ─ 뮤직포스트)","contents":"주간 핫이슈","link":"https://music.bugs.co.kr/musicpost/S0GSCIMJ29UOC22CWRSM?&wl_ref=list_sp_01_h","retrieved":1691615402588,"image":"https://image.bugsm.co.kr/uniContent/banner/S0GSCIMJ29UOC22CWRSM/title_mobile_306.jpg"},{"title":"몽림(Mongrim) - '술래' MV 촬영 비하인드 공개! (벅스 ─ 뮤직포스트)","contents":"주간 핫이슈","link":"https://music.bugs.co.kr/musicpost/GK5EZ7R0XPBTI4BCH40V?&wl_ref=list_sp_01_h","retrieved":1691615402588,"image":"https://image.bugsm.co.kr/uniContent/banner/GK5EZ7R0XPBTI4BCH40V/title_mobile_306.jpg"},{"title":"김양 - '엄정화'의 크로스와 Poison을 재탄생시킨 [Kim Yang Cross] 발매 기념 인터뷰 (벅스 ─ 뮤직포스트)","contents":"주간 핫이슈","link":"https://music.bugs.co.kr/musicpost/Y7BC0G354XR9KHZ14D7G?&wl_ref=list_sp_01_h","retrieved":1691615402589,"image":"https://image.bugsm.co.kr/uniContent/banner/Y7BC0G354XR9KHZ14D7G/title_mobile_306.jpg"},{"title":"팝송으로 배우는 영어! 72.Lauv - 'Steal The Show' (벅스 ─ 뮤직포스트)","contents":"뮤직&amp;","link":"https://music.bugs.co.kr/musicpost/PAXCJCO7QFGO2HTHBFVS?&wl_ref=list_sp_01_h","retrieved":1691615402589},{"title":"뭘 들을까? - 2023년 7월 노래 모음! (벅스 ─ 뮤직포스트)","contents":"뮤직&amp;","link":"https://music.bugs.co.kr/musicpost/8VMUTVPN46YTQQB9P2SK?&wl_ref=list_sp_01_h","retrieved":1691615402589},{"title":"Alan Walker(알렌 워커) - 여름의 뜨거운 더위를 한번에 날려버릴 흥겨운 비트와 환상적인 멜로디 [Endless Summer] (벅스 ─ 뮤직포스트)","contents":"주간 핫이슈","link":"https://music.bugs.co.kr/musicpost/XXKFCO637UNYJL60H74K?&wl_ref=list_sp_01_h","retrieved":1691615402589,"image":"https://image.bugsm.co.kr/uniContent/banner/XXKFCO637UNYJL60H74K/title_mobile_306.jpg"},{"title":"모트(Motte) - '쉿' 일본 공연 비하인드 공개! (벅스 ─ 뮤직포스트)","contents":"주간 핫이슈","link":"https://music.bugs.co.kr/musicpost/D12SQMXRVWJ3A5TWW0XB?&wl_ref=list_sp_01_h","retrieved":1691615402590,"image":"https://image.bugsm.co.kr/uniContent/banner/D12SQMXRVWJ3A5TWW0XB/title_mobile_306.jpg"},{"title":"Leo (리오) - 달달한 사랑에 빠진 Leo (리오)의 [Vanilla] (벅스 ─ 뮤직포스트)","contents":"주간 핫이슈","link":"https://music.bugs.co.kr/musicpost/E7FL4LTGKW6X1H0GHK5Y?&wl_ref=list_sp_01_h","retrieved":1691615402590,"image":"https://image.bugsm.co.kr/uniContent/banner/E7FL4LTGKW6X1H0GHK5Y/title_mobile_306.jpg"},{"title":"유다빈밴드 - 청춘을 노래하는 밴드의 학창 시절 대공개! (벅스 ─ 뮤직포스트)","contents":"주간 핫이슈","link":"https://music.bugs.co.kr/musicpost/UR7DS3IJ57W31V4XZG3R?&wl_ref=list_sp_01_h","retrieved":1691615402602,"image":"https://image.bugsm.co.kr/uniContent/banner/UR7DS3IJ57W31V4XZG3R/title_mobile_306.jpg"},{"title":"8TURN - 익숙함에 물든 세상을 깨울 8TURN(에잇턴)의 한여름 밤의 소동 [UNCHARTED DRIFT] (벅스 ─ 뮤직포스트)","contents":"주간 핫이슈","link":"https://music.bugs.co.kr/musicpost/SGE80P2SDWBVESVRZOMC?&wl_ref=list_sp_01_h","retrieved":1691615402602,"image":"https://image.bugsm.co.kr/uniContent/banner/SGE80P2SDWBVESVRZOMC/title_mobile_306.jpg"},{"title":"Lapillus(라필루스) - 올 여름 시즌을 물들일 [GIRL's ROUND Part. 2] 자켓 촬영 비하인드 (벅스 ─ 뮤직포스트)","contents":"주간 핫이슈","link":"https://music.bugs.co.kr/musicpost/KS6LZFNSS2EYSDJE68FB?&wl_ref=list_sp_01_h","retrieved":1691615402603,"image":"https://image.bugsm.co.kr/uniContent/banner/KS6LZFNSS2EYSDJE68FB/title_mobile_306.jpg"},{"title":"팝송으로 배우는 영어! 71.Jeremy Zucker - 'OK' (벅스 ─ 뮤직포스트)","contents":"뮤직&amp;","link":"https://music.bugs.co.kr/musicpost/L3OLE42L0D90620W909A?&wl_ref=list_sp_01_h","retrieved":1691615402603},{"title":"레인보우 노트(Rainbow note) - 'Summer party' MV 비하인드 공개! (벅스 ─ 뮤직포스트)","contents":"주간 핫이슈","link":"https://music.bugs.co.kr/musicpost/9FUH8YLTL2DTYMBL5FCV?&wl_ref=list_sp_01_h","retrieved":1691615402606,"image":"https://image.bugsm.co.kr/uniContent/banner/9FUH8YLTL2DTYMBL5FCV/title_mobile_306.jpg"},{"title":"뭘 들을까? - 2023년 6월 노래 모음! (벅스 ─ 뮤직포스트)","contents":"뮤직&amp;","link":"https://music.bugs.co.kr/musicpost/24WD6BOO2GXXKI9E5EYV?&wl_ref=list_sp_01_h","retrieved":1691615402607},{"title":"한살차이 - 정규앨범 타이틀 곡 '그리워했나요' MV 촬영 스케치! (벅스 ─ 뮤직포스트)","contents":"주간 핫이슈","link":"https://music.bugs.co.kr/musicpost/EJ968J2T73NYBCCF2YTG?&wl_ref=list_sp_01_h","retrieved":1691615402607,"image":"https://image.bugsm.co.kr/uniContent/banner/EJ968J2T73NYBCCF2YTG/title_mobile_306.jpg"},{"title":"Maaya Sakamoto(사카모토 마아야/坂本 真綾) - 정규 11집 [記憶の図書館(Kioku no Toshokan)] 발매 기념 인터뷰 (벅스 ─ 뮤직포스트)","contents":"주간 핫이슈","link":"https://music.bugs.co.kr/musicpost/H70SRLDR1QAUA3WP2VRG?&wl_ref=list_sp_01_h","retrieved":1691615402607,"image":"https://image.bugsm.co.kr/uniContent/banner/H70SRLDR1QAUA3WP2VRG/title_mobile_306.jpg"},{"title":"SECRET NUMBER (시크릿넘버) - 독보다 더 독한 모습으로 돌아온 싱글 6집 [독사 (DOXA)] (벅스 ─ 뮤직포스트)","contents":"주간 핫이슈","link":"https://music.bugs.co.kr/musicpost/D5PY4N0YBRKSPGJ5RRPJ?&wl_ref=list_sp_01_h","retrieved":1691615402619,"image":"https://image.bugsm.co.kr/uniContent/banner/D5PY4N0YBRKSPGJ5RRPJ/title_mobile_306.jpg"},{"title":"팝송으로 배우는 영어! 70.Post Malone - 'Chemical' (벅스 ─ 뮤직포스트)","contents":"뮤직&amp;","link":"https://music.bugs.co.kr/musicpost/XWQ5HRLX13Q6EDO3W1BE?&wl_ref=list_sp_01_h","retrieved":1691615402620},{"title":"우리가 쌓아온 그 기쁨들, ADOY [PLEASURES] MV 비하인드 공개 (지니 ─ 매거진)","contents":"스페셜","link":"https://genie.co.kr/magazine/subMain?ctid=1&mgz_seq=13521&pg=1","retrieved":1693473067576,"image":"https://image.genie.co.kr/Y/IMAGE/IMG_MUZICAT/IV2/Genie_Magazine/13521/Mgz_Main_List_20230831112436.jpg/dims/resize/Q_80,0"},{"title":"아티스트 백호, 디지털 싱글 프로젝트 ‘the [bæd] time’ 가동 (지니 ─ 매거진)","contents":"스페셜","link":"https://genie.co.kr/magazine/subMain?ctid=1&mgz_seq=13516&pg=1","retrieved":1693473067579,"image":"https://image.genie.co.kr/Y/IMAGE/IMG_MUZICAT/IV2/Genie_Magazine/13516/Mgz_Main_List_20230831142118.jpg/dims/resize/Q_80,0"},{"title":"비아이지 (B.I.G)의 ‘WANT’ 퍼포먼스 비디오 촬영 스케치 (지니 ─ 매거진)","contents":"스페셜","link":"https://genie.co.kr/magazine/subMain?ctid=1&mgz_seq=13514&pg=1","retrieved":1693473067582,"image":"https://image.genie.co.kr/Y/IMAGE/IMG_MUZICAT/IV2/Genie_Magazine/13514/Mgz_Main_List_20230831150201.jpg/dims/resize/Q_80,0"},{"title":"쿠바를 좋아하세요? - 해럴드 로페스 누사 ＜Timba a la America... (지니 ─ 매거진)","contents":"클래식 공감","link":"https://genie.co.kr/magazine/subMain?ctid=8&mgz_seq=13519&pg=1","retrieved":1693455181004,"image":"https://image.genie.co.kr/Y/IMAGE/IMG_MUZICAT/IV2/Genie_Magazine/13519/Mgz_Main_List_20230831103221.jpg/dims/resize/Q_80,0"},{"title":"프랑스 영화 같은 하루를 위한 플레이리스트 (지니 ─ 매거진)","contents":"스페셜","link":"https://genie.co.kr/magazine/subMain?ctid=1&mgz_seq=13515&pg=1","retrieved":1693455181006,"image":"https://image.genie.co.kr/Y/IMAGE/IMG_MUZICAT/IV2/Genie_Magazine/13515/Mgz_Main_List_20230831110716.jpg/dims/resize/Q_80,0"},{"title":"가요 탐구생활 ＃58 - 다시 불어오는 록 밴드의 붐 (지니 ─ 매거진)","contents":"가요 탐구생활","link":"https://genie.co.kr/magazine/subMain?ctid=27&mgz_seq=13513&pg=1","retrieved":1693386661822,"image":"https://image.genie.co.kr/Y/IMAGE/IMG_MUZICAT/IV2/Genie_Magazine/13513/Mgz_Main_List_20230830155959.jpg/dims/resize/Q_80,0"},{"title":"김우진 미니 2집 [The moment : 美成年, Bounce.] 자켓 촬영... (지니 ─ 매거진)","contents":"스페셜","link":"https://genie.co.kr/magazine/subMain?ctid=1&mgz_seq=13512&pg=1","retrieved":1693386661827,"image":"https://image.genie.co.kr/Y/IMAGE/IMG_MUZICAT/IV2/Genie_Magazine/13512/Mgz_Main_List_20230830162437.jpg/dims/resize/Q_80,0"},{"title":"＃낭만드러머 ＃아티스트그잡채 ＃제주랑인디 'DK' 편 (지니 ─ 매거진)","contents":"#왓_인_플","link":"https://genie.co.kr/magazine/subMain?ctid=40&mgz_seq=13511&pg=1","retrieved":1693386661829,"image":"https://image.genie.co.kr/Y/IMAGE/IMG_MUZICAT/IV2/Genie_Magazine/13511/Mgz_Main_List_20230830150132.jpg/dims/resize/Q_80,0"},{"title":"New Release #158 : \n악뮤, 셀레나 고메즈 (VIBE ─ 매거진)","contents":"<span data-v-269b06c8=\"\" class=\"blind\">작성일</span> 2023.08.28","link":"https://vibe.naver.com/magazines/62374","retrieved":1693383262475,"image":"https://music-phinf.pstatic.net/20230828_100/169320861186365WXJ_JPEG/%C4%BF%B9%F61.jpg?type=w720"},{"title":"한국 힙합의 게임 체인저 : \nMC 메타, 드렁큰 타이거 (VIBE ─ 매거진)","contents":"<span data-v-269b06c8=\"\" class=\"blind\">작성일</span> 2023.08.25","link":"https://vibe.naver.com/magazines/62373","retrieved":1693213919337,"image":"https://music-phinf.pstatic.net/20230825_68/1692926329692fyJqb_JPEG/%C4%BF%B9%F61.jpg?type=w720"},{"title":"이주의 디깅 #165 \n오펜하이머 (VIBE ─ 매거진)","contents":"<span data-v-269b06c8=\"\" class=\"blind\">작성일</span> 2023.08.24","link":"https://vibe.naver.com/magazines/62372","retrieved":1692951236018,"image":"https://music-phinf.pstatic.net/20230823_48/1692778966061ymdOD_JPEG/%C4%BF%B9%F61.jpg?type=w720"},{"title":"김준수, \n20년의 약속 (VIBE ─ 매거진)","contents":"<span data-v-269b06c8=\"\" class=\"blind\">작성일</span> 2023.08.22","link":"https://vibe.naver.com/magazines/62371","retrieved":1692868290174,"image":"data:image/png;base64,iVBORw0KGgoAAAANSUhEUgAAAZAAAAGQAQMAAAC6caSPAAAABGdBTUEAALGPC/xhBQAAAAFzUkdCAK7OHOkAAAAGUExURRoaGhERETZTak8AAAIlSURBVHja7doxbsIwGMVx0wyR2iHcIEfxUTgKPhpbV47gsWOGDgwINzgqOCQo339oFbUvQweLH++TIQnQ59Kzwz09RERERERERERERER+l9SYvKUASbVPMOWlX4ApowUT2Sea4hNN2Q0LIKV+XLATpShldSkXj1MCJsF5ONihP5tZytFR8pGvGWSwz+EyQ1IiJ53Dg0UNpsE02B8ZbIsHqxMerGX3lzh8IgtssE3CKRW6i/n3ONwwzCn9SP1gDUnpnz8OxJzS5pSWpPic4knKPqd4kpJwyvU17IaP41ZSDSmUwJT6lnIhpGOkuaWcIek3+cRJR8jh+52GSJP/2knIGxfIJofrK3pxhOSHnRx4w+Tnfw2EnOE38U25u+azMlLii921XpRO+oVERERERERERERE5J8R7YuIiIiIiIiIiIjIWkiNyb2+ZyVFfc9IyvqekZQrNnL9Tx5L8Ymm7IYVkPJYrQJEKUpZXcq9vmcmAZOivmckh6L2YiNHR8m4vmchD/U9C4mcPBSFfihFg2kwDbbKwbZ4sKK+Z01p2f0lulF9zzjYJuGUCt3FJvW9RTKt7y2SaX1vkbQ5pSUpflKsWyT7nOJJSsIpM/W9JTJT37MQmDJT37OQjpEmTep7RuKL+p6ddIQcxvU9I2mK+p6FhHF9z7LJYVzfs5D8OHPfca6+ZyBn+E18pr5nOCsjJdP63vJF6aRfSERERERERERERERE8vEF75usLCqqK/sAAAAASUVORK5CYII="},{"title":"New Release #157 : \n지효, 찰리푸스 (VIBE ─ 매거진)","contents":"<span data-v-269b06c8=\"\" class=\"blind\">작성일</span> 2023.08.21","link":"https://vibe.naver.com/magazines/62370","retrieved":1692695463614,"image":"data:image/png;base64,iVBORw0KGgoAAAANSUhEUgAAAZAAAAGQAQMAAAC6caSPAAAABGdBTUEAALGPC/xhBQAAAAFzUkdCAK7OHOkAAAAGUExURRoaGhERETZTak8AAAIlSURBVHja7doxbsIwGMVx0wyR2iHcIEfxUTgKPhpbV47gsWOGDgwINzgqOCQo339oFbUvQweLH++TIQnQ59Kzwz09RERERERERERERER+l9SYvKUASbVPMOWlX4ApowUT2Sea4hNN2Q0LIKV+XLATpShldSkXj1MCJsF5ONihP5tZytFR8pGvGWSwz+EyQ1IiJ53Dg0UNpsE02B8ZbIsHqxMerGX3lzh8IgtssE3CKRW6i/n3ONwwzCn9SP1gDUnpnz8OxJzS5pSWpPic4knKPqd4kpJwyvU17IaP41ZSDSmUwJT6lnIhpGOkuaWcIek3+cRJR8jh+52GSJP/2knIGxfIJofrK3pxhOSHnRx4w+Tnfw2EnOE38U25u+azMlLii921XpRO+oVERERERERERERE5J8R7YuIiIiIiIiIiIjIWkiNyb2+ZyVFfc9IyvqekZQrNnL9Tx5L8Ymm7IYVkPJYrQJEKUpZXcq9vmcmAZOivmckh6L2YiNHR8m4vmchD/U9C4mcPBSFfihFg2kwDbbKwbZ4sKK+Z01p2f0lulF9zzjYJuGUCt3FJvW9RTKt7y2SaX1vkbQ5pSUpflKsWyT7nOJJSsIpM/W9JTJT37MQmDJT37OQjpEmTep7RuKL+p6ddIQcxvU9I2mK+p6FhHF9z7LJYVzfs5D8OHPfca6+ZyBn+E18pr5nOCsjJdP63vJF6aRfSERERERERERERERE8vEF75usLCqqK/sAAAAASUVORK5CYII="},{"title":"나얼, \n확장되는 음악세계 (VIBE ─ 매거진)","contents":"<span data-v-269b06c8=\"\" class=\"blind\">작성일</span> 2023.08.16","link":"https://vibe.naver.com/magazines/62369","retrieved":1692612742698,"image":"data:image/png;base64,iVBORw0KGgoAAAANSUhEUgAAAZAAAAGQAQMAAAC6caSPAAAABGdBTUEAALGPC/xhBQAAAAFzUkdCAK7OHOkAAAAGUExURRoaGhERETZTak8AAAIlSURBVHja7doxbsIwGMVx0wyR2iHcIEfxUTgKPhpbV47gsWOGDgwINzgqOCQo339oFbUvQweLH++TIQnQ59Kzwz09RERERERERERERER+l9SYvKUASbVPMOWlX4ApowUT2Sea4hNN2Q0LIKV+XLATpShldSkXj1MCJsF5ONihP5tZytFR8pGvGWSwz+EyQ1IiJ53Dg0UNpsE02B8ZbIsHqxMerGX3lzh8IgtssE3CKRW6i/n3ONwwzCn9SP1gDUnpnz8OxJzS5pSWpPic4knKPqd4kpJwyvU17IaP41ZSDSmUwJT6lnIhpGOkuaWcIek3+cRJR8jh+52GSJP/2knIGxfIJofrK3pxhOSHnRx4w+Tnfw2EnOE38U25u+azMlLii921XpRO+oVERERERERERERE5J8R7YuIiIiIiIiIiIjIWkiNyb2+ZyVFfc9IyvqekZQrNnL9Tx5L8Ymm7IYVkPJYrQJEKUpZXcq9vmcmAZOivmckh6L2YiNHR8m4vmchD/U9C4mcPBSFfihFg2kwDbbKwbZ4sKK+Z01p2f0lulF9zzjYJuGUCt3FJvW9RTKt7y2SaX1vkbQ5pSUpflKsWyT7nOJJSsIpM/W9JTJT37MQmDJT37OQjpEmTep7RuKL+p6ddIQcxvU9I2mK+p6FhHF9z7LJYVzfs5D8OHPfca6+ZyBn+E18pr5nOCsjJdP63vJF6aRfSERERERERERERERE8vEF75usLCqqK/sAAAAASUVORK5CYII="},{"title":"New Release #156 : \n뷔, 올리비아 로드리고 (VIBE ─ 매거진)","contents":"<span data-v-269b06c8=\"\" class=\"blind\">작성일</span> 2023.08.14","link":"https://vibe.naver.com/magazines/62368","retrieved":1692169908090,"image":"data:image/png;base64,iVBORw0KGgoAAAANSUhEUgAAAZAAAAGQAQMAAAC6caSPAAAABGdBTUEAALGPC/xhBQAAAAFzUkdCAK7OHOkAAAAGUExURRoaGhERETZTak8AAAIlSURBVHja7doxbsIwGMVx0wyR2iHcIEfxUTgKPhpbV47gsWOGDgwINzgqOCQo339oFbUvQweLH++TIQnQ59Kzwz09RERERERERERERER+l9SYvKUASbVPMOWlX4ApowUT2Sea4hNN2Q0LIKV+XLATpShldSkXj1MCJsF5ONihP5tZytFR8pGvGWSwz+EyQ1IiJ53Dg0UNpsE02B8ZbIsHqxMerGX3lzh8IgtssE3CKRW6i/n3ONwwzCn9SP1gDUnpnz8OxJzS5pSWpPic4knKPqd4kpJwyvU17IaP41ZSDSmUwJT6lnIhpGOkuaWcIek3+cRJR8jh+52GSJP/2knIGxfIJofrK3pxhOSHnRx4w+Tnfw2EnOE38U25u+azMlLii921XpRO+oVERERERERERERE5J8R7YuIiIiIiIiIiIjIWkiNyb2+ZyVFfc9IyvqekZQrNnL9Tx5L8Ymm7IYVkPJYrQJEKUpZXcq9vmcmAZOivmckh6L2YiNHR8m4vmchD/U9C4mcPBSFfihFg2kwDbbKwbZ4sKK+Z01p2f0lulF9zzjYJuGUCt3FJvW9RTKt7y2SaX1vkbQ5pSUpflKsWyT7nOJJSsIpM/W9JTJT37MQmDJT37OQjpEmTep7RuKL+p6ddIQcxvU9I2mK+p6FhHF9z7LJYVzfs5D8OHPfca6+ZyBn+E18pr5nOCsjJdP63vJF6aRfSERERERERERERERE8vEF75usLCqqK/sAAAAASUVORK5CYII="},{"title":"조유리, \n사랑스럽게 직진 (VIBE ─ 매거진)","contents":"<span data-v-269b06c8=\"\" class=\"blind\">작성일</span> 2023.08.11","link":"https://vibe.naver.com/magazines/62367","retrieved":1692004360837,"image":"data:image/png;base64,iVBORw0KGgoAAAANSUhEUgAAAZAAAAGQAQMAAAC6caSPAAAABGdBTUEAALGPC/xhBQAAAAFzUkdCAK7OHOkAAAAGUExURRoaGhERETZTak8AAAIlSURBVHja7doxbsIwGMVx0wyR2iHcIEfxUTgKPhpbV47gsWOGDgwINzgqOCQo339oFbUvQweLH++TIQnQ59Kzwz09RERERERERERERER+l9SYvKUASbVPMOWlX4ApowUT2Sea4hNN2Q0LIKV+XLATpShldSkXj1MCJsF5ONihP5tZytFR8pGvGWSwz+EyQ1IiJ53Dg0UNpsE02B8ZbIsHqxMerGX3lzh8IgtssE3CKRW6i/n3ONwwzCn9SP1gDUnpnz8OxJzS5pSWpPic4knKPqd4kpJwyvU17IaP41ZSDSmUwJT6lnIhpGOkuaWcIek3+cRJR8jh+52GSJP/2knIGxfIJofrK3pxhOSHnRx4w+Tnfw2EnOE38U25u+azMlLii921XpRO+oVERERERERERERE5J8R7YuIiIiIiIiIiIjIWkiNyb2+ZyVFfc9IyvqekZQrNnL9Tx5L8Ymm7IYVkPJYrQJEKUpZXcq9vmcmAZOivmckh6L2YiNHR8m4vmchD/U9C4mcPBSFfihFg2kwDbbKwbZ4sKK+Z01p2f0lulF9zzjYJuGUCt3FJvW9RTKt7y2SaX1vkbQ5pSUpflKsWyT7nOJJSsIpM/W9JTJT37MQmDJT37OQjpEmTep7RuKL+p6ddIQcxvU9I2mK+p6FhHF9z7LJYVzfs5D8OHPfca6+ZyBn+E18pr5nOCsjJdP63vJF6aRfSERERERERERERERE8vEF75usLCqqK/sAAAAASUVORK5CYII="},{"title":"테크토닉 \n소미 (VIBE ─ 매거진)","contents":"<span data-v-269b06c8=\"\" class=\"blind\">작성일</span> 2023.08.09","link":"https://vibe.naver.com/magazines/62366","retrieved":1691737882921,"image":"data:image/png;base64,iVBORw0KGgoAAAANSUhEUgAAAZAAAAGQAQMAAAC6caSPAAAABGdBTUEAALGPC/xhBQAAAAFzUkdCAK7OHOkAAAAGUExURRoaGhERETZTak8AAAIlSURBVHja7doxbsIwGMVx0wyR2iHcIEfxUTgKPhpbV47gsWOGDgwINzgqOCQo339oFbUvQweLH++TIQnQ59Kzwz09RERERERERERERER+l9SYvKUASbVPMOWlX4ApowUT2Sea4hNN2Q0LIKV+XLATpShldSkXj1MCJsF5ONihP5tZytFR8pGvGWSwz+EyQ1IiJ53Dg0UNpsE02B8ZbIsHqxMerGX3lzh8IgtssE3CKRW6i/n3ONwwzCn9SP1gDUnpnz8OxJzS5pSWpPic4knKPqd4kpJwyvU17IaP41ZSDSmUwJT6lnIhpGOkuaWcIek3+cRJR8jh+52GSJP/2knIGxfIJofrK3pxhOSHnRx4w+Tnfw2EnOE38U25u+azMlLii921XpRO+oVERERERERERERE5J8R7YuIiIiIiIiIiIjIWkiNyb2+ZyVFfc9IyvqekZQrNnL9Tx5L8Ymm7IYVkPJYrQJEKUpZXcq9vmcmAZOivmckh6L2YiNHR8m4vmchD/U9C4mcPBSFfihFg2kwDbbKwbZ4sKK+Z01p2f0lulF9zzjYJuGUCt3FJvW9RTKt7y2SaX1vkbQ5pSUpflKsWyT7nOJJSsIpM/W9JTJT37MQmDJT37OQjpEmTep7RuKL+p6ddIQcxvU9I2mK+p6FhHF9z7LJYVzfs5D8OHPfca6+ZyBn+E18pr5nOCsjJdP63vJF6aRfSERERERERERERERE8vEF75usLCqqK/sAAAAASUVORK5CYII="},{"title":"이주의 디깅 #164 \n트래비스 스캇 (VIBE ─ 매거진)","contents":"<span data-v-269b06c8=\"\" class=\"blind\">작성일</span> 2023.08.08","link":"https://vibe.naver.com/magazines/62365","retrieved":1691561719001,"image":"data:image/png;base64,iVBORw0KGgoAAAANSUhEUgAAAZAAAAGQAQMAAAC6caSPAAAABGdBTUEAALGPC/xhBQAAAAFzUkdCAK7OHOkAAAAGUExURRoaGhERETZTak8AAAIlSURBVHja7doxbsIwGMVx0wyR2iHcIEfxUTgKPhpbV47gsWOGDgwINzgqOCQo339oFbUvQweLH++TIQnQ59Kzwz09RERERERERERERER+l9SYvKUASbVPMOWlX4ApowUT2Sea4hNN2Q0LIKV+XLATpShldSkXj1MCJsF5ONihP5tZytFR8pGvGWSwz+EyQ1IiJ53Dg0UNpsE02B8ZbIsHqxMerGX3lzh8IgtssE3CKRW6i/n3ONwwzCn9SP1gDUnpnz8OxJzS5pSWpPic4knKPqd4kpJwyvU17IaP41ZSDSmUwJT6lnIhpGOkuaWcIek3+cRJR8jh+52GSJP/2knIGxfIJofrK3pxhOSHnRx4w+Tnfw2EnOE38U25u+azMlLii921XpRO+oVERERERERERERE5J8R7YuIiIiIiIiIiIjIWkiNyb2+ZyVFfc9IyvqekZQrNnL9Tx5L8Ymm7IYVkPJYrQJEKUpZXcq9vmcmAZOivmckh6L2YiNHR8m4vmchD/U9C4mcPBSFfihFg2kwDbbKwbZ4sKK+Z01p2f0lulF9zzjYJuGUCt3FJvW9RTKt7y2SaX1vkbQ5pSUpflKsWyT7nOJJSsIpM/W9JTJT37MQmDJT37OQjpEmTep7RuKL+p6ddIQcxvU9I2mK+p6FhHF9z7LJYVzfs5D8OHPfca6+ZyBn+E18pr5nOCsjJdP63vJF6aRfSERERERERERERERE8vEF75usLCqqK/sAAAAASUVORK5CYII="},{"title":"New Release #155 : \n인피니트, 도자 캣 (VIBE ─ 매거진)","contents":"<span data-v-269b06c8=\"\" class=\"blind\">작성일</span> 2023.08.07","link":"https://vibe.naver.com/magazines/62364","retrieved":1691497230080,"image":"data:image/png;base64,iVBORw0KGgoAAAANSUhEUgAAAZAAAAGQAQMAAAC6caSPAAAABGdBTUEAALGPC/xhBQAAAAFzUkdCAK7OHOkAAAAGUExURRoaGhERETZTak8AAAIlSURBVHja7doxbsIwGMVx0wyR2iHcIEfxUTgKPhpbV47gsWOGDgwINzgqOCQo339oFbUvQweLH++TIQnQ59Kzwz09RERERERERERERER+l9SYvKUASbVPMOWlX4ApowUT2Sea4hNN2Q0LIKV+XLATpShldSkXj1MCJsF5ONihP5tZytFR8pGvGWSwz+EyQ1IiJ53Dg0UNpsE02B8ZbIsHqxMerGX3lzh8IgtssE3CKRW6i/n3ONwwzCn9SP1gDUnpnz8OxJzS5pSWpPic4knKPqd4kpJwyvU17IaP41ZSDSmUwJT6lnIhpGOkuaWcIek3+cRJR8jh+52GSJP/2knIGxfIJofrK3pxhOSHnRx4w+Tnfw2EnOE38U25u+azMlLii921XpRO+oVERERERERERERE5J8R7YuIiIiIiIiIiIjIWkiNyb2+ZyVFfc9IyvqekZQrNnL9Tx5L8Ymm7IYVkPJYrQJEKUpZXcq9vmcmAZOivmckh6L2YiNHR8m4vmchD/U9C4mcPBSFfihFg2kwDbbKwbZ4sKK+Z01p2f0lulF9zzjYJuGUCt3FJvW9RTKt7y2SaX1vkbQ5pSUpflKsWyT7nOJJSsIpM/W9JTJT37MQmDJT37OQjpEmTep7RuKL+p6ddIQcxvU9I2mK+p6FhHF9z7LJYVzfs5D8OHPfca6+ZyBn+E18pr5nOCsjJdP63vJF6aRfSERERERERERERERE8vEF75usLCqqK/sAAAAASUVORK5CYII="},{"title":"싸이커스로의 \n여행 (VIBE ─ 매거진)","contents":"<span data-v-269b06c8=\"\" class=\"blind\">작성일</span> 2023.08.02","link":"https://vibe.naver.com/magazines/62363","retrieved":1691410885597,"image":"data:image/png;base64,iVBORw0KGgoAAAANSUhEUgAAAZAAAAGQAQMAAAC6caSPAAAABGdBTUEAALGPC/xhBQAAAAFzUkdCAK7OHOkAAAAGUExURRoaGhERETZTak8AAAIlSURBVHja7doxbsIwGMVx0wyR2iHcIEfxUTgKPhpbV47gsWOGDgwINzgqOCQo339oFbUvQweLH++TIQnQ59Kzwz09RERERERERERERER+l9SYvKUASbVPMOWlX4ApowUT2Sea4hNN2Q0LIKV+XLATpShldSkXj1MCJsF5ONihP5tZytFR8pGvGWSwz+EyQ1IiJ53Dg0UNpsE02B8ZbIsHqxMerGX3lzh8IgtssE3CKRW6i/n3ONwwzCn9SP1gDUnpnz8OxJzS5pSWpPic4knKPqd4kpJwyvU17IaP41ZSDSmUwJT6lnIhpGOkuaWcIek3+cRJR8jh+52GSJP/2knIGxfIJofrK3pxhOSHnRx4w+Tnfw2EnOE38U25u+azMlLii921XpRO+oVERERERERERERE5J8R7YuIiIiIiIiIiIjIWkiNyb2+ZyVFfc9IyvqekZQrNnL9Tx5L8Ymm7IYVkPJYrQJEKUpZXcq9vmcmAZOivmckh6L2YiNHR8m4vmchD/U9C4mcPBSFfihFg2kwDbbKwbZ4sKK+Z01p2f0lulF9zzjYJuGUCt3FJvW9RTKt7y2SaX1vkbQ5pSUpflKsWyT7nOJJSsIpM/W9JTJT37MQmDJT37OQjpEmTep7RuKL+p6ddIQcxvU9I2mK+p6FhHF9z7LJYVzfs5D8OHPfca6+ZyBn+E18pr5nOCsjJdP63vJF6aRfSERERERERERERERE8vEF75usLCqqK/sAAAAASUVORK5CYII="},{"title":"Ready, Set, \n예린 (VIBE ─ 매거진)","contents":"예린이 다시 출발선에 선다. 우리 곁의 친근한 여자친구에서 중독성 강한 멜로디에 아련함 몇 방울을 얹은 신선하고 세련된 모습으로.","retrieved":1693529487004,"image":"https://music-phinf.pstatic.net/20230829_268/1693297588960R8fqN_GIF/%C4%BF%B9%F62.gif?type=w840"},{"title":"풍요로운 가을을 품은 제철 요리 (현대카드 DIVE ─ POST)","contents":"쿠킹 라이브러리 9월 먼슬리 스페셜","link":"javascript:;","retrieved":1691583793600,"image":"https://dive.hyundaicard.com/resources/images/upload/content/0e6a254e1a3f40e99dfa72dba0522cd2.jpg"},{"title":"디자인이 우리에게 말해 주는 것들 (현대카드 DIVE ─ POST)","contents":"디자인 라이브러리 9월의 새 책","link":"javascript:;","retrieved":1691583793600,"image":"https://dive.hyundaicard.com/resources/images/upload/content/613e8d30e73743f0a0e09d1d687aa6e8.jpg"},{"title":"전설의 세션들 (현대카드 DIVE ─ POST)","contents":"V&amp;P 9월 Monthly Special","link":"javascript:;","retrieved":1691583793600,"image":"https://dive.hyundaicard.com/resources/images/upload/content/5a05986356414d32b58c1a1ac6722692.jpg"},{"title":"가장 진보적인 시도들 (현대카드 DIVE ─ POST)","contents":"뮤직 라이브러리 9월의 컬렉션","link":"javascript:;","retrieved":1691583793600,"image":"https://dive.hyundaicard.com/resources/images/upload/content/a71fa69fd1884874821db66be643d228.jpg"},{"title":"장인과 신예들 (현대카드 DIVE ─ POST)","contents":"현대카드 뮤직 라이브러리 9월의 새 음반","link":"javascript:;","retrieved":1691583793600,"image":"https://dive.hyundaicard.com/resources/images/upload/content/243d7ad0e61048089c97c20c1c571d21.jpg"},{"title":"피사체의 본질과 오라 (현대카드 DIVE ─ POST)","contents":"9월의 디자이너 David Bailey","link":"javascript:;","retrieved":1691583793600,"image":"https://dive.hyundaicard.com/resources/images/upload/content/99ef04c0a14047dd8da3d0f6f90ecd8e.jpg"},{"title":"예술가의 유일무이한 세계 (현대카드 DIVE ─ POST)","contents":"현대카드 아트 라이브러리 9월의 새 책","link":"javascript:;","retrieved":1691583793600,"image":"https://dive.hyundaicard.com/resources/images/upload/content/abb0733ef8f549ceae76cfea6ed6bdc0.jpg"},{"title":"예술가의 표현, 초상, 궤적 (현대카드 DIVE ─ POST)","contents":"현대카드 아트 라이브러리 레어 북 컬렉션","link":"javascript:;","retrieved":1691583793600,"image":"https://dive.hyundaicard.com/resources/images/upload/content/679d6493a44b4785910f52a1ba3e8936.jpg"},{"title":"24프레임의 미학 (현대카드 DIVE ─ POST)","contents":"아트 라이브러리 MoMA 테마 북 컬렉션","link":"javascript:;","retrieved":1691583793600,"image":"https://dive.hyundaicard.com/resources/images/upload/content/79f7e0a58b7344118eb5e7890fdc5f84.jpg"}]}