{"title":"빌보드 코리아 ─ 뉴스","url":"http://billboard.co.kr/main/news/list","favicon":"http://billboard.co.kr/images/favi/android-icon-192x192.png","elements":[{"title":"소코도모 ‘회전목마’, 빌보드 케이팝 100 차트 3주 연속 1위","contents":"<a href=\"/main/news/view/747\">\n\t\t\t\t\t\t\t\t<!-- <span class=\"label_crown\"><img src=\"../images/main2/label_crown.png\" alt=\"라벨\"></span> -->\n                                <div class=\"img-boxs\">\n                                    <div class=\"img-con\">\n\t\t\t\t\t\t\t\t        <img src=\"/upload_data/board/simg/20211214190642_15.png\" alt=\"소코도모 ‘회전목마’, 빌보드 케이팝 100 차트 3주 연속 1위\" style=\"width:100%;\">\n                                    </div>\n                                </div>\n\t\t\t\t\t\t\t\t<div class=\"txt\">\n\t\t\t\t\t\t\t\t\t<span>소코도모 ‘회전목마’, 빌보드 케이팝 100 차트 3주 연속 1위</span>\n\t\t\t\t\t\t\t\t\t<div class=\"sub_title\"></div>\n\t\t\t\t\t\t\t\t</div>\n\t\t\t\t\t\t\t</a>","link":"http://billboard.co.kr/main/news/view/747","retrieved":1639477310020,"image":"http://billboard.co.kr/upload_data/board/simg/20211214190642_15.png"},{"title":"이달의 빌보드 HOT 100 총정리(11/13~12/4)","contents":"<a href=\"/main/news/view/746\">\n\t\t\t\t\t\t\t\t<!-- <span class=\"label_crown\"><img src=\"../images/main2/label_crown.png\" alt=\"라벨\"></span> -->\n                                <div class=\"img-boxs\">\n                                    <div class=\"img-con\">\n\t\t\t\t\t\t\t\t        <img src=\"/upload_data/board/simg/20211208181327_3.png\" alt=\"이달의 빌보드 HOT 100 총정리(11/13~12/4)\" style=\"width:100%;\">\n                                    </div>\n                                </div>\n\t\t\t\t\t\t\t\t<div class=\"txt\">\n\t\t\t\t\t\t\t\t\t<span>이달의 빌보드 HOT 100 총정리(11/13~12/4)</span>\n\t\t\t\t\t\t\t\t\t<div class=\"sub_title\"></div>\n\t\t\t\t\t\t\t\t</div>\n\t\t\t\t\t\t\t</a>","link":"http://billboard.co.kr/main/news/view/746","retrieved":1638955212400,"image":"http://billboard.co.kr/upload_data/board/simg/20211208181327_3.png"},{"title":"소코도모 ‘회전목마’, 빌보드 케이팝 100 차트 2주 연속 1위","contents":"<a href=\"/main/news/view/745\">\n\t\t\t\t\t\t\t\t<!-- <span class=\"label_crown\"><img src=\"../images/main2/label_crown.png\" alt=\"라벨\"></span> -->\n                                <div class=\"img-boxs\">\n                                    <div class=\"img-con\">\n\t\t\t\t\t\t\t\t        <img src=\"/upload_data/board/simg/20211207163534_18.png\" alt=\"소코도모 ‘회전목마’, 빌보드 케이팝 100 차트 2주 연속 1위\" style=\"width:100%;\">\n                                    </div>\n                                </div>\n\t\t\t\t\t\t\t\t<div class=\"txt\">\n\t\t\t\t\t\t\t\t\t<span>소코도모 ‘회전목마’, 빌보드 케이팝 100 차트 2주 연속 1위</span>\n\t\t\t\t\t\t\t\t\t<div class=\"sub_title\"></div>\n\t\t\t\t\t\t\t\t</div>\n\t\t\t\t\t\t\t</a>","link":"http://billboard.co.kr/main/news/view/745","retrieved":1638872610790,"image":"http://billboard.co.kr/upload_data/board/simg/20211207163534_18.png"},{"title":"[English Column by Jeff Benjamin] How to enjoy your “K-Vibe Festa” this Winter","contents":"<a href=\"/main/news/view/744\">\n\t\t\t\t\t\t\t\t<!-- <span class=\"label_crown\"><img src=\"../images/main2/label_crown.png\" alt=\"라벨\"></span> -->\n                                <div class=\"img-boxs\">\n                                    <div class=\"img-con\">\n\t\t\t\t\t\t\t\t        <img src=\"/upload_data/board/simg/20211206180230_11.jpg\" alt=\"[English Column by Jeff Benjamin] How to enjoy your “K-Vibe Festa” this Winter\" style=\"width:100%;\">\n                                    </div>\n                                </div>\n\t\t\t\t\t\t\t\t<div class=\"txt\">\n\t\t\t\t\t\t\t\t\t<span>[English Column by Jeff Benjamin] How to enjoy your “K-Vibe Festa” this Winter</span>\n\t\t\t\t\t\t\t\t\t<div class=\"sub_title\"></div>\n\t\t\t\t\t\t\t\t</div>\n\t\t\t\t\t\t\t</a>","link":"http://billboard.co.kr/main/news/view/744","retrieved":1638782436679,"image":"http://billboard.co.kr/upload_data/board/simg/20211206180230_11.jpg"},{"title":"[English Column by Riddhi Chakraborty] How to enjoy your “K-Vibe Festa” this Winter","contents":"<a href=\"/main/news/view/743\">\n\t\t\t\t\t\t\t\t<!-- <span class=\"label_crown\"><img src=\"../images/main2/label_crown.png\" alt=\"라벨\"></span> -->\n                                <div class=\"img-boxs\">\n                                    <div class=\"img-con\">\n\t\t\t\t\t\t\t\t        <img src=\"/upload_data/board/simg/20211206180152_6.jpg\" alt=\"[English Column by Riddhi Chakraborty] How to enjoy your “K-Vibe Festa” this Winter\" style=\"width:100%;\">\n                                    </div>\n                                </div>\n\t\t\t\t\t\t\t\t<div class=\"txt\">\n\t\t\t\t\t\t\t\t\t<span>[English Column by Riddhi Chakraborty] How to enjoy your “K-Vibe Festa” this Winter</span>\n\t\t\t\t\t\t\t\t\t<div class=\"sub_title\"></div>\n\t\t\t\t\t\t\t\t</div>\n\t\t\t\t\t\t\t</a>","link":"http://billboard.co.kr/main/news/view/743","retrieved":1638782436681,"image":"http://billboard.co.kr/upload_data/board/simg/20211206180152_6.jpg"},{"title":"한국의 진짜 멋을 담다, Feel The Rhythm of Korea : Season2","contents":"<a href=\"/main/news/view/742\">\n\t\t\t\t\t\t\t\t<!-- <span class=\"label_crown\"><img src=\"../images/main2/label_crown.png\" alt=\"라벨\"></span> -->\n                                <div class=\"img-boxs\">\n                                    <div class=\"img-con\">\n\t\t\t\t\t\t\t\t        <img src=\"/upload_data/board/simg/20211203163029_0.jpg\" alt=\"한국의 진짜 멋을 담다, Feel The Rhythm of Korea : Season2\" style=\"width:100%;\">\n                                    </div>\n                                </div>\n\t\t\t\t\t\t\t\t<div class=\"txt\">\n\t\t\t\t\t\t\t\t\t<span>한국의 진짜 멋을 담다, Feel The Rhythm of Korea : Season2</span>\n\t\t\t\t\t\t\t\t\t<div class=\"sub_title\"></div>\n\t\t\t\t\t\t\t\t</div>\n\t\t\t\t\t\t\t</a>","link":"http://billboard.co.kr/main/news/view/742","retrieved":1638523196907,"image":"http://billboard.co.kr/upload_data/board/simg/20211203163029_0.jpg"},{"title":"NCT, 정규 3집 타이틀곡 선공개","contents":"<a href=\"/main/news/view/741\">\n\t\t\t\t\t\t\t\t<!-- <span class=\"label_crown\"><img src=\"../images/main2/label_crown.png\" alt=\"라벨\"></span> -->\n                                <div class=\"img-boxs\">\n                                    <div class=\"img-con\">\n\t\t\t\t\t\t\t\t        <img src=\"/upload_data/board/simg/20211202180031_0.jpg\" alt=\"NCT, 정규 3집 타이틀곡 선공개\" style=\"width:100%;\">\n                                    </div>\n                                </div>\n\t\t\t\t\t\t\t\t<div class=\"txt\">\n\t\t\t\t\t\t\t\t\t<span>NCT, 정규 3집 타이틀곡 선공개</span>\n\t\t\t\t\t\t\t\t\t<div class=\"sub_title\"></div>\n\t\t\t\t\t\t\t\t</div>\n\t\t\t\t\t\t\t</a>","link":"http://billboard.co.kr/main/news/view/741","retrieved":1638436767177,"image":"http://billboard.co.kr/upload_data/board/simg/20211202180031_0.jpg"},{"title":"한국 여행과 K-POP 아티스트가 총출동한 콘서트를 동시에, K-VIBE CONCERT","contents":"<a href=\"/main/news/view/740\">\n\t\t\t\t\t\t\t\t<!-- <span class=\"label_crown\"><img src=\"../images/main2/label_crown.png\" alt=\"라벨\"></span> -->\n                                <div class=\"img-boxs\">\n                                    <div class=\"img-con\">\n\t\t\t\t\t\t\t\t        <img src=\"/upload_data/board/simg/20211201183908_26.png\" alt=\"한국 여행과 K-POP 아티스트가 총출동한 콘서트를 동시에, K-VIBE CONCERT\" style=\"width:100%;\">\n                                    </div>\n                                </div>\n\t\t\t\t\t\t\t\t<div class=\"txt\">\n\t\t\t\t\t\t\t\t\t<span>한국 여행과 K-POP 아티스트가 총출동한 콘서트를 동시에, K-VIBE CONCERT</span>\n\t\t\t\t\t\t\t\t\t<div class=\"sub_title\"></div>\n\t\t\t\t\t\t\t\t</div>\n\t\t\t\t\t\t\t</a>","link":"http://billboard.co.kr/main/news/view/740","retrieved":1638354095978,"image":"http://billboard.co.kr/upload_data/board/simg/20211201183908_26.png"},{"title":"소코도모 ‘회전목마’, 빌보드 케이팝 100 차트 정상 등극","contents":"<a href=\"/main/news/view/739\">\n\t\t\t\t\t\t\t\t<!-- <span class=\"label_crown\"><img src=\"../images/main2/label_crown.png\" alt=\"라벨\"></span> -->\n                                <div class=\"img-boxs\">\n                                    <div class=\"img-con\">\n\t\t\t\t\t\t\t\t        <img src=\"/upload_data/board/simg/20211130185646_2.png\" alt=\"소코도모 ‘회전목마’, 빌보드 케이팝 100 차트 정상 등극\" style=\"width:100%;\">\n                                    </div>\n                                </div>\n\t\t\t\t\t\t\t\t<div class=\"txt\">\n\t\t\t\t\t\t\t\t\t<span>소코도모 ‘회전목마’, 빌보드 케이팝 100 차트 정상 등극</span>\n\t\t\t\t\t\t\t\t\t<div class=\"sub_title\"></div>\n\t\t\t\t\t\t\t\t</div>\n\t\t\t\t\t\t\t</a>","link":"http://billboard.co.kr/main/news/view/739","retrieved":1638267492384,"image":"http://billboard.co.kr/upload_data/board/simg/20211130185646_2.png"}]}