{"title":"지니 ─ 매거진","url":"https://genie.co.kr/magazine","favicon":"https://genie.co.kr/favicon.ico","elements":[{"title":"꿈 많은 청춘들의 이야기, LUN8(루네이트)의 [BUFF] 뮤비 촬영 비하인...","contents":"스페셜","link":"https://genie.co.kr/magazine/subMain?ctid=1&mgz_seq=14089&pg=1","retrieved":1710321128691,"image":"https://image.genie.co.kr/Y/IMAGE/IMG_MUZICAT/IV2/Genie_Magazine/14089/Mgz_Main_List_20240312110520.jpg/dims/resize/Q_80,0"},{"title":"BAE173의 새로운 챕터 [NEW CHAPTER : LUCEAT] 자켓 촬영...","contents":"스페셜","link":"https://genie.co.kr/magazine/subMain?ctid=1&mgz_seq=14084&pg=1","retrieved":1710321128692,"image":"https://image.genie.co.kr/Y/IMAGE/IMG_MUZICAT/IV2/Genie_Magazine/14084/Mgz_Main_List_20240313141147.jpg/dims/resize/Q_80,0"},{"title":"팬들에게 전하는 따뜻한 위로, 우리를 위한 ‘더 좋은 기다림’ 황민현 [Lul...","contents":"스페셜","link":"https://genie.co.kr/magazine/subMain?ctid=1&mgz_seq=14081&pg=1","retrieved":1710321128692,"image":"https://image.genie.co.kr/Y/IMAGE/IMG_MUZICAT/IV2/Genie_Magazine/14081/Mgz_Main_List_20240313140834.jpg/dims/resize/Q_80,0"},{"title":"VVUP(비비업), Win-UP을 향한 긴 여정의 시작!","contents":"스페셜","link":"https://genie.co.kr/magazine/subMain?ctid=1&mgz_seq=14088&pg=1","retrieved":1710299623256,"image":"https://image.genie.co.kr/Y/IMAGE/IMG_MUZICAT/IV2/Genie_Magazine/14088/Mgz_Main_List_20240312164825.jpg/dims/resize/Q_80,0"},{"title":"재즈덩크 ＃62 - 어벤져스급 올스타 세션의 파워와 쾌감! 'Chris Pot...","contents":"MM JAZZ","link":"https://genie.co.kr/magazine/subMain?ctid=6&mgz_seq=14093&pg=1","retrieved":1710234847770,"image":"https://image.genie.co.kr/Y/IMAGE/IMG_MUZICAT/IV2/Genie_Magazine/14093/Mgz_Main_List_20240312164236.jpg/dims/resize/Q_80,0"},{"title":"진정한 웬디를 찾아가는 과정! 미니 2집 [Wish You Hell] 전격 공...","contents":"스페셜","link":"https://genie.co.kr/magazine/subMain?ctid=1&mgz_seq=14086&pg=1","retrieved":1710234847771,"image":"https://image.genie.co.kr/Y/IMAGE/IMG_MUZICAT/IV2/Genie_Magazine/14086/Mgz_Main_List_20240312105633.jpg/dims/resize/Q_80,0"},{"title":"bow-wow 발매 기념 Lacuna (라쿠나) 성수동 게릴라 라이브 현장 공...","contents":"스페셜","link":"https://genie.co.kr/magazine/subMain?ctid=1&mgz_seq=14085&pg=1","retrieved":1710213258004,"image":"https://image.genie.co.kr/Y/IMAGE/IMG_MUZICAT/IV2/Genie_Magazine/14085/Mgz_Main_List_20240312105458.jpg/dims/resize/Q_80,0"},{"title":"나의 존경을 담아, 브후빈더가 연주하는 브람스-레거: 가곡 편곡집","contents":"클래식 공감","link":"https://genie.co.kr/magazine/subMain?ctid=8&mgz_seq=14082&pg=1","retrieved":1710213258005,"image":"https://image.genie.co.kr/Y/IMAGE/IMG_MUZICAT/IV2/Genie_Magazine/14082/Mgz_Main_List_20240311103121.jpg/dims/resize/Q_80,0"}]}