{"title":"지니 ─ 매거진","url":"https://genie.co.kr/magazine","favicon":"https://genie.co.kr/favicon.ico","elements":[{"title":"재즈 하는 하프 – 브랜디 영거의 [Brand New Life]","contents":"클래식 공감","link":"https://genie.co.kr/magazine/subMain?ctid=8&mgz_seq=13240&pg=1","retrieved":1686107849721,"image":"https://image.genie.co.kr/Y/IMAGE/IMG_MUZICAT/IV2/Genie_Magazine/13240/Mgz_Main_List_20230607092927.jpg/dims/resize/Q_80,0"},{"title":"‘그럼에도 우리 나아가자!’ 김뮤즈 첫 자작곡 [택배]를 발매하기까지","contents":"스페셜","link":"https://genie.co.kr/magazine/subMain?ctid=1&mgz_seq=13239&pg=1","retrieved":1686107849724,"image":"https://image.genie.co.kr/Y/IMAGE/IMG_MUZICAT/IV2/Genie_Magazine/13239/Mgz_Main_List_20230605175509.jpg/dims/resize/Q_80,0"},{"title":"보이는 바다와 그 아래 해저, 수면을 오가는 듯한 깊이 있는 에너지 – 밀릭 ...","contents":"스페셜","link":"https://genie.co.kr/magazine/subMain?ctid=1&mgz_seq=13236&pg=1","retrieved":1686107849726,"image":"https://image.genie.co.kr/Y/IMAGE/IMG_MUZICAT/IV2/Genie_Magazine/13236/Mgz_Main_List_20230607094105.jpg/dims/resize/Q_80,0"},{"title":"‘태용’답기에 빛날 수밖에 없는, 미니 1집 [SHALALA]","contents":"스페셜","link":"https://genie.co.kr/magazine/subMain?ctid=1&mgz_seq=13234&pg=1","retrieved":1685963428047,"image":"https://image.genie.co.kr/Y/IMAGE/IMG_MUZICAT/IV2/Genie_Magazine/13234/Mgz_Main_List_20230607141053.jpg/dims/resize/Q_80,0"},{"title":"EK [I was bad vibin'] MV 촬영 현장 공개","contents":"스페셜","link":"https://genie.co.kr/magazine/subMain?ctid=1&mgz_seq=13232&pg=1","retrieved":1685963428047,"image":"https://image.genie.co.kr/Y/IMAGE/IMG_MUZICAT/IV2/Genie_Magazine/13232/Mgz_Main_List_20230605152006.jpg/dims/resize/Q_80,0"},{"title":"당당하고 솔직한 매력! 프로미스나인 첫 정규 앨범 [Unlock My Worl...","contents":"스페셜","link":"https://genie.co.kr/magazine/subMain?ctid=1&mgz_seq=13228&pg=1","retrieved":1685963428047,"image":"https://image.genie.co.kr/Y/IMAGE/IMG_MUZICAT/IV2/Genie_Magazine/13228/Mgz_Main_List_20230605145205.jpg/dims/resize/Q_80,0"},{"title":"밥과 재방문을 부르는 신기한 술집, <금호 미주리>","contents":"핫플힙플","link":"https://genie.co.kr/magazine/subMain?ctid=16&mgz_seq=13235&pg=1","retrieved":1685934868432,"image":"https://image.genie.co.kr/Y/IMAGE/IMG_MUZICAT/IV2/Genie_Magazine/13234/Mgz_Main_List_20230605113845.jpg/dims/resize/Q_80,0"},{"title":"뉴욕 브루클린 인디 씬을 자유롭게 유영하는 로파이 드림팝 밴드, Beach F...","contents":"스페셜","link":"https://genie.co.kr/magazine/subMain?ctid=1&mgz_seq=13231&pg=1","retrieved":1685934868434,"image":"https://image.genie.co.kr/Y/IMAGE/IMG_MUZICAT/IV2/Genie_Magazine/13231/Mgz_Main_List_20230605091639.jpg/dims/resize/Q_80,0"}]}