{"title":"지니 ─ 매거진","url":"https://genie.co.kr/magazine","favicon":"https://genie.co.kr/favicon.ico","elements":[{"title":"음악의 시작과 끝, 인간의 목소리를 듣다","contents":"클래식 공감","link":"https://genie.co.kr/magazine/subMain?ctid=8&mgz_seq=14061&pg=1","retrieved":1709003576129,"image":"https://image.genie.co.kr/Y/IMAGE/IMG_MUZICAT/IV2/Genie_Magazine/14061/Mgz_Main_List_20240227110910.jpg/dims/resize/Q_80,0"},{"title":"몬트(M.O.N.T) ‘마음대로 해(IDGAF)’ 뮤직비디오 촬영 현장 비하인...","contents":"스페셜","link":"https://genie.co.kr/magazine/subMain?ctid=1&mgz_seq=14056&pg=1","retrieved":1709003576130,"image":"https://image.genie.co.kr/Y/IMAGE/IMG_MUZICAT/IV2/Genie_Magazine/14056/Mgz_Main_List_20240227104323.jpg/dims/resize/Q_80,0"},{"title":"지치고 위로가 필요한 이들을 위한 메세지, Jaemun [두려운게 많아] 발매...","contents":"스페셜","link":"https://genie.co.kr/magazine/subMain?ctid=1&mgz_seq=14051&pg=1","retrieved":1709003576132,"image":"https://image.genie.co.kr/Y/IMAGE/IMG_MUZICAT/IV2/Genie_Magazine/14051/Mgz_Main_List_20240227112922.jpg/dims/resize/Q_80,0"},{"title":"가요 탐구생활 ＃64 - 한순간에 마음을 흔들어놓은 역대급 남자 아이돌 데뷔곡","contents":"가요 탐구생활","link":"https://genie.co.kr/magazine/subMain?ctid=27&mgz_seq=14060&pg=1","retrieved":1708938744424,"image":"https://image.genie.co.kr/Y/IMAGE/IMG_MUZICAT/IV2/Genie_Magazine/14060/Mgz_Main_List_20240226173551.jpg/dims/resize/Q_80,0"},{"title":"크래비티에게 펼쳐질 모든 날들은 [EVERSHINE]","contents":"스페셜","link":"https://genie.co.kr/magazine/subMain?ctid=1&mgz_seq=14055&pg=1","retrieved":1708938744425,"image":"https://image.genie.co.kr/Y/IMAGE/IMG_MUZICAT/IV2/Genie_Magazine/14055/Mgz_Main_List_20240226145555.jpg/dims/resize/Q_80,0"},{"title":"미추어버리겠어! 기리보이 새 싱글 [미춰버리겠어] 프로필 촬영 현장 공개","contents":"스페셜","link":"https://genie.co.kr/magazine/subMain?ctid=1&mgz_seq=14054&pg=1","retrieved":1708938744426,"image":"https://image.genie.co.kr/Y/IMAGE/IMG_MUZICAT/IV2/Genie_Magazine/14054/Mgz_Main_List_20240226144946.jpg/dims/resize/Q_80,0"},{"title":"태용의 관심 표현법이 궁금하다면? 지금 바로 [TAP]!","contents":"스페셜","link":"https://genie.co.kr/magazine/subMain?ctid=1&mgz_seq=14050&pg=1","retrieved":1708938744428,"image":"https://image.genie.co.kr/Y/IMAGE/IMG_MUZICAT/IV2/Genie_Magazine/14050/Mgz_Main_List_20240226153547.jpg/dims/resize/Q_80,0"},{"title":"KIMKIMPARKKIM's 음악가, 함께 ＃19 - Lionel Richie","contents":"김김박김","link":"https://genie.co.kr/magazine/subMain?ctid=36&mgz_seq=14057&pg=1","retrieved":1708917205407,"image":"https://image.genie.co.kr/Y/IMAGE/IMG_MUZICAT/IV2/Genie_Magazine/14057/Mgz_Main_List_20240226104120.jpg/dims/resize/Q_80,0"}]}