{"title":"지니 ─ 매거진","url":"https://genie.co.kr/magazine","favicon":"https://genie.co.kr/favicon.ico","elements":[{"title":"반짝반짝 꿈나라 여행, 라인프렌즈 [클래식 자장가4 – 작은별 변주곡]","contents":"스페셜","link":"https://genie.co.kr/magazine/subMain?ctid=1&mgz_seq=14985&pg=1","retrieved":1737602151548,"image":"https://image.genie.co.kr/Y/IMAGE/IMG_MUZICAT/IV2/Genie_Magazine/14985/Mgz_Main_List_20250123111055.jpg/dims/resize/Q_80,0"},{"title":"요한 슈트라우스 2세 탄생 200주년, 춤추고 싶은 자 그의 음악을 들어라","contents":"클래식 공감","link":"https://genie.co.kr/magazine/subMain?ctid=8&mgz_seq=14984&pg=1","retrieved":1737602151549,"image":"https://image.genie.co.kr/Y/IMAGE/IMG_MUZICAT/IV2/Genie_Magazine/14983/Mgz_Main_List_20250123103810.jpg/dims/resize/Q_80,0"},{"title":"하디아 첫 앨범 [DIA] & 첫 단독 온라인 콘서트 [DIA] 제작기","contents":"스페셜","link":"https://genie.co.kr/magazine/subMain?ctid=1&mgz_seq=14971&pg=1","retrieved":1737602151551,"image":"https://image.genie.co.kr/Y/IMAGE/IMG_MUZICAT/IV2/Genie_Magazine/14971/Mgz_Main_List_20250123103130.jpg/dims/resize/Q_80,0"},{"title":"옥토넛의 아이스 어드벤처! ＜바다 탐험대 옥토넛 : 극지방 대작전＞","contents":"스페셜","link":"https://genie.co.kr/magazine/subMain?ctid=1&mgz_seq=14976&pg=1","retrieved":1737515843418,"image":"https://image.genie.co.kr/Y/IMAGE/IMG_MUZICAT/IV2/Genie_Magazine/14976/Mgz_Main_List_20250122105943.jpg/dims/resize/Q_80,0"},{"title":"소각소각 신곡 ‘안아줘’ 발매 기념 인터뷰","contents":"스페셜","link":"https://genie.co.kr/magazine/subMain?ctid=1&mgz_seq=14967&pg=1","retrieved":1737515843420,"image":"https://image.genie.co.kr/Y/IMAGE/IMG_MUZICAT/IV2/Genie_Magazine/14967/Mgz_Main_List_20250121105041.jpg/dims/resize/Q_80,0"},{"title":"다채로운 색깔로 가득 채운 민니의 첫 번째 이야기 [HER] 자켓 촬영 현장 ...","contents":"스페셜","link":"https://genie.co.kr/magazine/subMain?ctid=1&mgz_seq=14970&pg=1","retrieved":1737450864903,"image":"https://image.genie.co.kr/Y/IMAGE/IMG_MUZICAT/IV2/Genie_Magazine/14970/Mgz_Main_List_20250120170637.jpg/dims/resize/Q_80,0"},{"title":"건반 위에서 그린 그림 - 피아니스트 조성진의 라벨 피아노 독주곡 전집","contents":"클래식 공감","link":"https://genie.co.kr/magazine/subMain?ctid=8&mgz_seq=14972&pg=1","retrieved":1737429338287,"image":"https://image.genie.co.kr/Y/IMAGE/IMG_MUZICAT/IV2/Genie_Magazine/14972/Mgz_Main_List_20250121111306.jpg/dims/resize/Q_80,0"},{"title":"‘메이플스토리’와 유럽 재즈의 자존심 ‘European Jazz Trio’의 ...","contents":"스페셜","link":"https://genie.co.kr/magazine/subMain?ctid=1&mgz_seq=14968&pg=1","retrieved":1737429338288,"image":"https://image.genie.co.kr/Y/IMAGE/IMG_MUZICAT/IV2/Genie_Magazine/14968/Mgz_Main_List_20250121104659.jpg/dims/resize/Q_80,0"}]}