{"title":"지니 ─ 매거진","url":"https://genie.co.kr/magazine","favicon":"https://genie.co.kr/favicon.ico","elements":[{"title":"퍼플키스(PURPLE KISS) ‘ON MY BIKE’ MV 촬영 현장","contents":"스페셜","link":"https://genie.co.kr/magazine/subMain?ctid=1&mgz_seq=14726&pg=1","retrieved":1729592107647,"image":"https://image.genie.co.kr/Y/IMAGE/IMG_MUZICAT/IV2/Genie_Magazine/14726/Mgz_Main_List_20241022140147.jpg/dims/resize/Q_80,0"},{"title":"느낌 좋은 앰퍼샌드원 (AMPERS&ONE) 의 ‘He + She = We’ ...","contents":"스페셜","link":"https://genie.co.kr/magazine/subMain?ctid=1&mgz_seq=14723&pg=1","retrieved":1729592107647,"image":"https://image.genie.co.kr/Y/IMAGE/IMG_MUZICAT/IV2/Genie_Magazine/14723/Mgz_Main_List_20241022143938.jpg/dims/resize/Q_80,0"},{"title":"재즈덩크 ＃69 - 제 연주의 가장 중요한 철학은 소통과 균형, 'Lewis ...","contents":"MM JAZZ","link":"https://genie.co.kr/magazine/subMain?ctid=6&mgz_seq=14732&pg=1","retrieved":1729567271647,"image":"https://image.genie.co.kr/Y/IMAGE/IMG_MUZICAT/IV2/Genie_Magazine/14732/Mgz_Main_List_20241022100821.jpg/dims/resize/Q_80,0"},{"title":"한없이 투명한 바흐 – 비킹구르 올라프손이 연주하는 바흐의 종교 음악","contents":"클래식 공감","link":"https://genie.co.kr/magazine/subMain?ctid=8&mgz_seq=14729&pg=1","retrieved":1729567271648,"image":"https://image.genie.co.kr/Y/IMAGE/IMG_MUZICAT/IV2/Genie_Magazine/14729/Mgz_Main_List_20241022101426.jpg/dims/resize/Q_80,0"},{"title":"한국 재즈에 관한 새로운 상상, 재즈보컬리스트 남예지의 <오래된 노래, 틈>","contents":"스페셜","link":"https://genie.co.kr/magazine/subMain?ctid=1&mgz_seq=14722&pg=1","retrieved":1729567271649,"image":"https://image.genie.co.kr/Y/IMAGE/IMG_MUZICAT/IV2/Genie_Magazine/14722/Mgz_Main_List_20241022102408.jpg/dims/resize/Q_80,0"},{"title":"패기 있는 고백 송으로 돌아온 POW (파우)의 2ND EP [Boyfrien...","contents":"스페셜","link":"https://genie.co.kr/magazine/subMain?ctid=1&mgz_seq=14725&pg=1","retrieved":1729502172743,"image":"https://image.genie.co.kr/Y/IMAGE/IMG_MUZICAT/IV2/Genie_Magazine/14725/Mgz_Main_List_20241021172328.jpg/dims/resize/Q_80,0"},{"title":"DXMON(다이몬)의 두 번째 싱글 앨범 [Youth Never DIE]의 ‘...","contents":"스페셜","link":"https://genie.co.kr/magazine/subMain?ctid=1&mgz_seq=14718&pg=1","retrieved":1729502172744,"image":"https://image.genie.co.kr/Y/IMAGE/IMG_MUZICAT/IV2/Genie_Magazine/14718/Mgz_Main_List_20241021100533.jpg/dims/resize/Q_80,0"},{"title":"Lacuna와의 콜라보레이션으로 돌아온 대만 밴드, Wendy Wander 깊...","contents":"스페셜","link":"https://genie.co.kr/magazine/subMain?ctid=1&mgz_seq=14724&pg=1","retrieved":1729481021362,"image":"https://image.genie.co.kr/Y/IMAGE/IMG_MUZICAT/IV2/Genie_Magazine/14724/Mgz_Main_List_20241021112418.jpg/dims/resize/Q_80,0"}]}