{"title":"지니 ─ 매거진","url":"https://genie.co.kr/magazine","favicon":"https://genie.co.kr/favicon.ico","elements":[{"title":"Goodbye 2023, Hello 2024! 대한민국 대표 클래식 스타들 총...","contents":"클래식 공감","link":"https://genie.co.kr/magazine/subMain?ctid=8&mgz_seq=13838&pg=1","retrieved":1701745945566,"image":"https://image.genie.co.kr/Y/IMAGE/IMG_MUZICAT/IV2/Genie_Magazine/13838/Mgz_Main_List_20231205114000.jpg/dims/resize/Q_80,0"},{"title":"“PUPPET” by 국카스텐 X 캐주얼 의류 브랜드 에이카","contents":"스페셜","link":"https://genie.co.kr/magazine/subMain?ctid=1&mgz_seq=13836&pg=1","retrieved":1701745945567,"image":"https://image.genie.co.kr/Y/IMAGE/IMG_MUZICAT/IV2/Genie_Magazine/13835/Mgz_Main_List_20231204135856.jpg/dims/resize/Q_80,0"},{"title":"묻어야 하는 추억에 대하여, 허회경 [난 묻어요] 발매 인터뷰","contents":"스페셜","link":"https://genie.co.kr/magazine/subMain?ctid=1&mgz_seq=13830&pg=1","retrieved":1701745945568,"image":"https://image.genie.co.kr/Y/IMAGE/IMG_MUZICAT/IV2/Genie_Magazine/13830/Mgz_Main_List_20231204151500.jpg/dims/resize/Q_80,0"},{"title":"재즈 뮤지션으로서의 본격적 도전, 시작점! '조윤성' 외","contents":"MM JAZZ","link":"https://genie.co.kr/magazine/subMain?ctid=6&mgz_seq=13835&pg=1","retrieved":1701688203813,"image":"https://image.genie.co.kr/Y/IMAGE/IMG_MUZICAT/IV2/Genie_Magazine/13835/Mgz_Main_List_20231204151023.jpg/dims/resize/Q_80,0"},{"title":"유키카 시티팝 리메이크앨범 Time-Lapse 뮤직비디오 비하인드 사진 공개!","contents":"스페셜","link":"https://genie.co.kr/magazine/subMain?ctid=1&mgz_seq=13831&pg=1","retrieved":1701688203814,"image":"https://image.genie.co.kr/Y/IMAGE/IMG_MUZICAT/IV2/Genie_Magazine/13831/Mgz_Main_List_20231204151129.jpg/dims/resize/Q_80,0"},{"title":"로맨틱한 사랑을 담은 새벽공방의 신곡 ‘Cinema’ 리릭 비디오 촬영 현장!","contents":"스페셜","link":"https://genie.co.kr/magazine/subMain?ctid=1&mgz_seq=13834&pg=1","retrieved":1701659529605,"image":"https://image.genie.co.kr/Y/IMAGE/IMG_MUZICAT/IV2/Genie_Magazine/13834/Mgz_Main_List_20231204091246.jpg/dims/resize/Q_80,0"},{"title":"차분해진 겨울 감성의 따뜻한 AVOKID (에이보키드) 의 새로운 EP앨범 “...","contents":"스페셜","link":"https://genie.co.kr/magazine/subMain?ctid=1&mgz_seq=13833&pg=1","retrieved":1701659529605,"image":"https://image.genie.co.kr/Y/IMAGE/IMG_MUZICAT/IV2/Genie_Magazine/13833/Mgz_Main_List_20231204101158.jpg/dims/resize/Q_80,0"},{"title":"정겨움과 따듯함이 공존하는 전통주 한식 주점 <잊힐리야 연남>","contents":"핫플힙플","link":"https://genie.co.kr/magazine/subMain?ctid=16&mgz_seq=13823&pg=1","retrieved":1701659529607,"image":"https://image.genie.co.kr/Y/IMAGE/IMG_MUZICAT/IV2/Genie_Magazine/13823/Mgz_Main_List_20231204111143.jpg/dims/resize/Q_80,0"}]}