{"title":"지니 ─ 매거진","url":"https://genie.co.kr/magazine","favicon":"https://genie.co.kr/favicon.ico","elements":[{"title":"봄이 되면 생각나는 뻔하지 않은 클래식","contents":"클래식 공감","link":"https://genie.co.kr/magazine/subMain?ctid=8&mgz_seq=11866&pg=1","retrieved":1649905335042,"image":"https://image.genie.co.kr/Y/IMAGE/IMG_MUZICAT/IV2/Genie_Magazine/11866/Mgz_Main_List_20220414105740.jpg/dims/resize/Q_80,0"},{"title":"'싱포레스트' OST 발매 기념 비하인드 컷 공개!","contents":"스페셜","link":"https://genie.co.kr/magazine/subMain?ctid=1&mgz_seq=11862&pg=1","retrieved":1649905335044,"image":"https://image.genie.co.kr/Y/IMAGE/IMG_MUZICAT/IV2/Genie_Magazine/11862/Mgz_Main_List_20220414104316.jpg/dims/resize/Q_80,0"},{"title":"이상민의 세 번째 싱글 앨범 [소리를 질러봐] 작업기","contents":"스페셜","link":"https://genie.co.kr/magazine/subMain?ctid=1&mgz_seq=11859&pg=1","retrieved":1649905335045,"image":"https://image.genie.co.kr/Y/IMAGE/IMG_MUZICAT/IV2/Genie_Magazine/11859/Mgz_Main_List_20220414100208.jpg/dims/resize/Q_80,0"},{"title":"그윽한 분위기와 설렘, ‘봄밤’에 찾아온 김필의 [봄밤 (Spring Nigh...","contents":"스페셜","link":"https://genie.co.kr/magazine/subMain?ctid=1&mgz_seq=11865&pg=1","retrieved":1649841198075,"image":"https://image.genie.co.kr/Y/IMAGE/IMG_MUZICAT/IV2/Genie_Magazine/11865/Mgz_Main_List_20220413142458.jpg/dims/resize/Q_80,0"},{"title":"봄날에 듣는 실내악 향연","contents":"스페셜","link":"https://genie.co.kr/magazine/subMain?ctid=1&mgz_seq=11855&pg=1","retrieved":1649841198078,"image":"https://image.genie.co.kr/Y/IMAGE/IMG_MUZICAT/IV2/Genie_Magazine/11855/Mgz_Main_List_20220413170616.jpg/dims/resize/Q_80,0"},{"title":"김동현 첫 솔로 데뷔! [Bittersweet] 라이브 클립 비하인드 현장","contents":"스페셜","link":"https://genie.co.kr/magazine/subMain?ctid=1&mgz_seq=11864&pg=1","retrieved":1649820876987,"image":"https://image.genie.co.kr/Y/IMAGE/IMG_MUZICAT/IV2/Genie_Magazine/11864/Mgz_Main_List_20220413120058.jpg/dims/resize/Q_80,0"},{"title":"클래식 핫스타! ‘레이어스 클래식’의 2집 앨범 [LOVE SIGNAL] 발매","contents":"스페셜","link":"https://genie.co.kr/magazine/subMain?ctid=1&mgz_seq=11861&pg=1","retrieved":1649820876989,"image":"https://image.genie.co.kr/Y/IMAGE/IMG_MUZICAT/IV2/Genie_Magazine/11861/Mgz_Main_List_20220413111850.jpg/dims/resize/Q_80,0"},{"title":"재즈덩크 ＃45 - 프로그레시브/아트 록에의 오마주 담아낸 동시대 재즈 사운드...","contents":"MM JAZZ","link":"https://genie.co.kr/magazine/subMain?ctid=6&mgz_seq=11809&pg=1","retrieved":1649820876994,"image":"https://image.genie.co.kr/Y/IMAGE/IMG_MUZICAT/IV2/Genie_Magazine/11809/Mgz_Main_List_20220412113046.jpg/dims/resize/Q_80,0"}]}