{"title":"지니 ─ 매거진","url":"https://genie.co.kr/magazine","favicon":"https://genie.co.kr/favicon.ico","elements":[{"title":"Loossemble (루셈블) 3rd Mini Album [TTYL] 자켓 촬...","contents":"스페셜","link":"https://genie.co.kr/magazine/subMain?ctid=1&mgz_seq=14594&pg=1","retrieved":1725268522725,"image":"https://image.genie.co.kr/Y/IMAGE/IMG_MUZICAT/IV2/Genie_Magazine/14594/Mgz_Main_List_20240902105003.jpg/dims/resize/Q_80,0"},{"title":"상처를 쓰다듬을 [Band Aid] 가 되어 찾아온 DAY6","contents":"스페셜","link":"https://genie.co.kr/magazine/subMain?ctid=1&mgz_seq=14589&pg=1","retrieved":1725268522726,"image":"https://image.genie.co.kr/Y/IMAGE/IMG_MUZICAT/IV2/Genie_Magazine/14589/Mgz_Main_List_20240902141342.jpg/dims/resize/Q_80,0"},{"title":"일상을 함께 벗어나 볼래요? 수아 (드림캐쳐)의 ‘틈 (Feel Alive)’...","contents":"스페셜","link":"https://genie.co.kr/magazine/subMain?ctid=1&mgz_seq=14588&pg=1","retrieved":1725268522730,"image":"https://image.genie.co.kr/Y/IMAGE/IMG_MUZICAT/IV2/Genie_Magazine/14588/Mgz_Main_List_20240902140951.jpg/dims/resize/Q_80,0"},{"title":"'새벽 2시의 신데렐라' OST Part. 3! 하현상 녹음실 비하인드 스토리","contents":"스페셜","link":"https://genie.co.kr/magazine/subMain?ctid=1&mgz_seq=14591&pg=1","retrieved":1725246920566,"image":"https://image.genie.co.kr/Y/IMAGE/IMG_MUZICAT/IV2/Genie_Magazine/14591/Mgz_Main_List_20240902104338.jpg/dims/resize/Q_80,0"},{"title":"떠나간 사람의 흔적에 대하여, can’t be blue [Blue Vinyl]","contents":"스페셜","link":"https://genie.co.kr/magazine/subMain?ctid=1&mgz_seq=14586&pg=1","retrieved":1725009293719,"image":"https://image.genie.co.kr/Y/IMAGE/IMG_MUZICAT/IV2/Genie_Magazine/14586/Mgz_Main_List_20240830104816.jpg/dims/resize/Q_80,0"},{"title":"백만 볼트 전기처럼 짜릿! 중독성과 신선함 모두 갖춘 LE SSERAFIM (...","contents":"스페셜","link":"https://genie.co.kr/magazine/subMain?ctid=1&mgz_seq=14584&pg=1","retrieved":1725009293719,"image":"https://image.genie.co.kr/Y/IMAGE/IMG_MUZICAT/IV2/Genie_Magazine/14584/Mgz_Main_List_20240830104519.jpg/dims/resize/Q_80,0"},{"title":"알앤비 따라잡기 ＃79 - 여름의 마지막, KR&B","contents":"힙알사전","link":"https://genie.co.kr/magazine/subMain?ctid=23&mgz_seq=14587&pg=1","retrieved":1724987664760,"image":"https://image.genie.co.kr/Y/IMAGE/IMG_MUZICAT/IV2/Genie_Magazine/14587/Mgz_Main_List_20240830111516.jpg/dims/resize/Q_80,0"},{"title":"로큰롤을 다스리는 어둠의 제왕, Nick Cave and the Bad See...","contents":"스페셜","link":"https://genie.co.kr/magazine/subMain?ctid=1&mgz_seq=14583&pg=1","retrieved":1724987664773,"image":"https://image.genie.co.kr/Y/IMAGE/IMG_MUZICAT/IV2/Genie_Magazine/14583/Mgz_Main_List_20240830104305.jpg/dims/resize/Q_80,0"}]}