{"title":"지니 ─ 매거진","url":"https://genie.co.kr/magazine","favicon":"https://genie.co.kr/favicon.ico","elements":[{"title":"THE BOYZ (더보이즈) The 3rd Album [Unexpected] ...","contents":"스페셜","link":"https://genie.co.kr/magazine/subMain?ctid=1&mgz_seq=15091&pg=1","retrieved":1742203059383,"image":"https://image.genie.co.kr/Y/IMAGE/IMG_MUZICAT/IV2/Genie_Magazine/15091/Mgz_Main_List_20250317112356.jpg/dims/resize/Q_80,0"},{"title":"더윈드, 끝없는 하늘에 어디서든 빛날 [Only One Story] 자켓 촬영...","contents":"스페셜","link":"https://genie.co.kr/magazine/subMain?ctid=1&mgz_seq=15088&pg=1","retrieved":1742203059384,"image":"https://image.genie.co.kr/Y/IMAGE/IMG_MUZICAT/IV2/Genie_Magazine/15088/Mgz_Main_List_20250317142340.jpg/dims/resize/Q_80,0"},{"title":"Fe3O4 시리즈의 마지막 이야기! NMIXX [Fe3O4: FORWARD]","contents":"스페셜","link":"https://genie.co.kr/magazine/subMain?ctid=1&mgz_seq=15086&pg=1","retrieved":1742203059385,"image":"https://image.genie.co.kr/Y/IMAGE/IMG_MUZICAT/IV2/Genie_Magazine/15086/Mgz_Main_List_20250317114800.jpg/dims/resize/Q_80,0"},{"title":"너무 많은 걸 담으려다 되레 어중간해진 수퍼 트리오, 'John Patituc...","contents":"MM JAZZ","link":"https://genie.co.kr/magazine/subMain?ctid=6&mgz_seq=15090&pg=1","retrieved":1742182154910,"image":"https://image.genie.co.kr/Y/IMAGE/IMG_MUZICAT/IV2/Genie_Magazine/15090/Mgz_Main_List_20250317110855.jpg/dims/resize/Q_80,0"},{"title":"힙합사의 결정적인 순간을 장식한 싱글들 86화","contents":"힙알사전","link":"https://genie.co.kr/magazine/subMain?ctid=23&mgz_seq=15089&pg=1","retrieved":1742182154913,"image":"https://image.genie.co.kr/Y/IMAGE/IMG_MUZICAT/IV2/Genie_Magazine/15089/Mgz_Main_List_20250317110821.jpg/dims/resize/Q_80,0"},{"title":"Risso의 미니앨범 [HE'S MY MELODY] 앨범제작기","contents":"스페셜","link":"https://genie.co.kr/magazine/subMain?ctid=1&mgz_seq=15087&pg=1","retrieved":1742182154913,"image":"https://image.genie.co.kr/Y/IMAGE/IMG_MUZICAT/IV2/Genie_Magazine/15087/Mgz_Main_List_20250317110755.jpg/dims/resize/Q_80,0"},{"title":"지니릴리가 전하는 Neo N (네오엔)의 음원 발매 소식 [밤 그리고 너]","contents":"스페셜","link":"https://genie.co.kr/magazine/subMain?ctid=1&mgz_seq=15081&pg=1","retrieved":1742182154915,"image":"https://image.genie.co.kr/Y/IMAGE/IMG_MUZICAT/IV2/Genie_Magazine/15081/Mgz_Main_List_20250312145013.jpg/dims/resize/Q_80,0"},{"title":"‘HOT’한 태도로 돌아온 LE SSERAFIM (르세라핌) – 미니 5집 ‘...","contents":"스페셜","link":"https://genie.co.kr/magazine/subMain?ctid=1&mgz_seq=15080&pg=1","retrieved":1741925834264,"image":"https://image.genie.co.kr/Y/IMAGE/IMG_MUZICAT/IV2/Genie_Magazine/15080/Mgz_Main_List_20250312162930.png/dims/resize/Q_80,0"}]}