{"title":"지니 ─ 매거진","url":"https://genie.co.kr/magazine","favicon":"https://genie.co.kr/favicon.ico","elements":[{"title":"개코 @Gaejaksill 프로젝트 제 4탄! [눈에 넣어도]","contents":"스페셜","link":"https://genie.co.kr/magazine/subMain?ctid=1&mgz_seq=11935&pg=1","retrieved":1651634534748,"image":"https://image.genie.co.kr/Y/IMAGE/IMG_MUZICAT/IV2/Genie_Magazine/11935/Mgz_Main_List_20220504111242.jpg/dims/resize/Q_80,0"},{"title":"알앤비 따라잡기 ＃52 - 한국 알앤비 이즈 고","contents":"힙알사전","link":"https://genie.co.kr/magazine/subMain?ctid=23&mgz_seq=11931&pg=1","retrieved":1651634534749,"image":"https://image.genie.co.kr/Y/IMAGE/IMG_MUZICAT/IV2/Genie_Magazine/11931/Mgz_Main_List_20220504103427.jpg/dims/resize/Q_80,0"},{"title":"구름 사이에 비치는 햇빛, 아티초크의 EP [Silver Lingings]","contents":"스페셜","link":"https://genie.co.kr/magazine/subMain?ctid=1&mgz_seq=11930&pg=1","retrieved":1651634534752,"image":"https://image.genie.co.kr/Y/IMAGE/IMG_MUZICAT/IV2/Genie_Magazine/11930/Mgz_Main_List_20220504112845.png/dims/resize/Q_80,0"},{"title":"어린왕자 려욱이 피워낸 〈A Wild Rose〉","contents":"스페셜","link":"https://genie.co.kr/magazine/subMain?ctid=1&mgz_seq=11934&pg=1","retrieved":1651569227790,"image":"https://image.genie.co.kr/Y/IMAGE/IMG_MUZICAT/IV2/Genie_Magazine/11934/Mgz_Main_List_20220503165347.jpg/dims/resize/Q_80,0"},{"title":"새로운 악장의 시작, 멜로망스 (MeloMance)의 축제로 ‘초대’","contents":"스페셜","link":"https://genie.co.kr/magazine/subMain?ctid=1&mgz_seq=11933&pg=1","retrieved":1651569227792,"image":"https://image.genie.co.kr/Y/IMAGE/IMG_MUZICAT/IV2/Genie_Magazine/11933/Mgz_Main_List_20220503165615.jpg/dims/resize/Q_80,0"},{"title":"iKON 4th MINI ALBUM [FLASHBACK] 미공개 비하인드 이미...","contents":"스페셜","link":"https://genie.co.kr/magazine/subMain?ctid=1&mgz_seq=11920&pg=1","retrieved":1651569227793,"image":"https://image.genie.co.kr/Y/IMAGE/IMG_MUZICAT/IV2/Genie_Magazine/11920/Mgz_Main_List_20220503165426.jpg/dims/resize/Q_80,0"},{"title":"재즈의 새로운 고전 ＃26 - 듀오 인터플레이 최정점에 오른 대가의 온화함과 ...","contents":"MM JAZZ","link":"https://genie.co.kr/magazine/subMain?ctid=6&mgz_seq=11923&pg=1","retrieved":1651558626733,"image":"https://image.genie.co.kr/Y/IMAGE/IMG_MUZICAT/IV2/Genie_Magazine/11923/Mgz_Main_List_20220503150703.jpg/dims/resize/Q_80,0"},{"title":"소울풀한 R&B 발라드로 돌아온 WINee의 새 싱글 [흔적]","contents":"스페셜","link":"https://genie.co.kr/magazine/subMain?ctid=1&mgz_seq=11932&pg=1","retrieved":1651548063997,"image":"https://image.genie.co.kr/Y/IMAGE/IMG_MUZICAT/IV2/Genie_Magazine/11932/Mgz_Main_List_20220503102707.jpg/dims/resize/Q_80,0"}]}