{"title":"지니 ─ 매거진","url":"https://genie.co.kr/magazine","favicon":"https://genie.co.kr/favicon.ico","elements":[{"title":"들려줘! 말해줘! L.O.V.E를 듣기 위한 트와이스의 미션 수행! [BETW...","contents":"스페셜","link":"https://genie.co.kr/magazine/subMain?ctid=1&mgz_seq=12335&pg=1","retrieved":1661487274861,"image":"https://image.genie.co.kr/Y/IMAGE/IMG_MUZICAT/IV2/Genie_Magazine/12335/Mgz_Main_List_20220826094606.jpg/dims/resize/Q_80,0"},{"title":"지니 컬러 동향 ＃48 – 2022.08.06 ~ 08.19 발매작","contents":"지니 컬러 동향","link":"https://genie.co.kr/magazine/subMain?ctid=33&mgz_seq=12337&pg=1","retrieved":1661487274861,"image":"https://image.genie.co.kr/Y/IMAGE/IMG_MUZICAT/IV2/Genie_Magazine/12337/Mgz_Main_List_20220826105016.jpg/dims/resize/Q_80,0"},{"title":"필윤의 정규 4집 앨범 네 번째 싱글 [Flight Seoul To North...","contents":"스페셜","link":"https://genie.co.kr/magazine/subMain?ctid=1&mgz_seq=12334&pg=1","retrieved":1661487274861,"image":"https://image.genie.co.kr/Y/IMAGE/IMG_MUZICAT/IV2/Genie_Magazine/12334/Mgz_Main_List_20220826093814.jpg/dims/resize/Q_80,0"},{"title":"섬세한 전달력을 지닌 호주 출신 싱어 송라이터 스텔라 도넬리의 2집 [Floo...","contents":"스페셜","link":"https://genie.co.kr/magazine/subMain?ctid=1&mgz_seq=12329&pg=1","retrieved":1661487274861,"image":"https://image.genie.co.kr/Y/IMAGE/IMG_MUZICAT/IV2/Genie_Magazine/12329/Mgz_Main_List_20220825110614.jpg/dims/resize/Q_80,0"},{"title":"24/7 함께하고 싶은 다크비의 [Autumn] 자켓 비하인드","contents":"스페셜","link":"https://genie.co.kr/magazine/subMain?ctid=1&mgz_seq=12336&pg=1","retrieved":1661418849771,"image":"https://image.genie.co.kr/Y/IMAGE/IMG_MUZICAT/IV2/Genie_Magazine/12336/Mgz_Main_List_20220825112749.jpg/dims/resize/Q_80,0"},{"title":"YOUHA (유하)의 첫 번째 EP [love you more,] 자켓 촬영 ...","contents":"스페셜","link":"https://genie.co.kr/magazine/subMain?ctid=1&mgz_seq=12333&pg=1","retrieved":1661418849774,"image":"https://image.genie.co.kr/Y/IMAGE/IMG_MUZICAT/IV2/Genie_Magazine/12333/Mgz_Main_List_20220824142234.jpg/dims/resize/Q_80,0"},{"title":"바로크 음악 새롭게 바라보기, 바흐, 헨델, 비발디 없는 바로크 시대?","contents":"클래식 공감","link":"https://genie.co.kr/magazine/subMain?ctid=8&mgz_seq=12332&pg=1","retrieved":1661400457616,"image":"https://image.genie.co.kr/Y/IMAGE/IMG_MUZICAT/IV2/Genie_Magazine/12332/Mgz_Main_List_20220824140927.jpg/dims/resize/Q_80,0"},{"title":"그레이트 서울 인베이전 2Round 미니 미션 & 3Round W24 촬영 비...","contents":"스페셜","link":"https://genie.co.kr/magazine/subMain?ctid=1&mgz_seq=12326&pg=1","retrieved":1661400457617,"image":"https://image.genie.co.kr/Y/IMAGE/IMG_MUZICAT/IV2/Genie_Magazine/12326/Mgz_Main_List_20220825103954.jpg/dims/resize/Q_80,0"}]}