{"title":"지니 ─ 매거진","url":"https://genie.co.kr/magazine","favicon":"https://genie.co.kr/favicon.ico","elements":[{"title":"오넷의 첫 번째 EP 앨범 [Citymare, Cityzone] 발매 기념 인...","contents":"스페셜","link":"https://genie.co.kr/magazine/subMain?ctid=1&mgz_seq=11683&pg=1","retrieved":1645693976991,"image":"https://image.genie.co.kr/Y/IMAGE/IMG_MUZICAT/IV2/Genie_Magazine/11683/Mgz_Main_List_20220224171347.jpg/dims/resize/Q_80,0"},{"title":"KIMKIMPARKKIM's 플레이리스트 가이드 ＃18 - 오늘 하루도 열심히...","contents":"김김박김","link":"https://genie.co.kr/magazine/subMain?ctid=36&mgz_seq=11687&pg=1","retrieved":1645683327692,"image":"https://image.genie.co.kr/Y/IMAGE/IMG_MUZICAT/IV2/Genie_Magazine/11687/Mgz_Main_List_20220224141251.jpg/dims/resize/Q_80,0"},{"title":"당신은 승리했습니다. 옥타브 올림픽에서... - (2) 옥타브의 예술가들","contents":"클래식 공감","link":"https://genie.co.kr/magazine/subMain?ctid=8&mgz_seq=11686&pg=1","retrieved":1645672309821,"image":"https://image.genie.co.kr/Y/IMAGE/IMG_MUZICAT/IV2/Genie_Magazine/11685/Mgz_Main_List_20220224091810.jpg/dims/resize/Q_80,0"},{"title":"“너의 충실한 사냥개가 되어주마” tvN <군검사 도베르만>","contents":"방송","link":"https://genie.co.kr/magazine/subMain?ctid=12&mgz_seq=11684&pg=1","retrieved":1645672309828,"image":"https://image.genie.co.kr/Y/IMAGE/IMG_MUZICAT/IV2/Genie_Magazine/11684/Mgz_Main_List_20220224105228.jpg/dims/resize/Q_80,0"},{"title":"Lacuna(라쿠나) 4th EP 타이틀곡 'YOU’ M/V 비하인드","contents":"스페셜","link":"https://genie.co.kr/magazine/subMain?ctid=1&mgz_seq=11681&pg=1","retrieved":1645672309829,"image":"https://image.genie.co.kr/Y/IMAGE/IMG_MUZICAT/IV2/Genie_Magazine/11681/Mgz_Main_List_20220224093333.jpg/dims/resize/Q_80,0"},{"title":"권은비의 첫 번째 OST [너와 나의 경찰수업 Part.4 ‘TIME’] 녹음...","contents":"스페셜","link":"https://genie.co.kr/magazine/subMain?ctid=1&mgz_seq=11680&pg=1","retrieved":1645607516295,"image":"https://image.genie.co.kr/Y/IMAGE/IMG_MUZICAT/IV2/Genie_Magazine/11679/Mgz_Main_List_20220222151410.jpg/dims/resize/Q_80,0"},{"title":"특별한 'Billlie'의 특별한 두 번째 미니 앨범 비하인드!","contents":"스페셜","link":"https://genie.co.kr/magazine/subMain?ctid=1&mgz_seq=11677&pg=1","retrieved":1645607516296,"image":"https://image.genie.co.kr/Y/IMAGE/IMG_MUZICAT/IV2/Genie_Magazine/11677/Mgz_Main_List_20220223142801.jpg/dims/resize/Q_80,0"},{"title":"스스로 관조하는 듯, 깊은 사색 내재된 피아노 음률, 'Ryuichi Saka...","contents":"MM JAZZ","link":"https://genie.co.kr/magazine/subMain?ctid=6&mgz_seq=11682&pg=1","retrieved":1645593131252,"image":"https://image.genie.co.kr/Y/IMAGE/IMG_MUZICAT/IV2/Genie_Magazine/11681/Mgz_Main_List_20220223122639.jpg/dims/resize/Q_80,0"}]}