{"title":"현대카드 DIVE ─ POST","url":"https://dive.hyundaicard.com/web/post/post.hdc","favicon":"https://dive.hyundaicard.com/web/post/favicon.ico","elements":[{"title":"맛있고  멋있는  채식","contents":"감각적인 채식 레스토랑 4","link":"javascript:;","retrieved":1640600647263,"image":"https://dive.hyundaicard.com/resources/images/upload/content/3526082dccce429a844de7addc6096dd.jpg"},{"title":"나를  추앙해요","contents":"예술을 머금은 아티스틱 화분 4","link":"javascript:;","retrieved":1640600647263,"image":"https://dive.hyundaicard.com/resources/images/upload/content/90bc7a4351ad431f824dbdf84409d398.jpg"},{"title":"NFT가  먹는 건가요?","contents":"NFT가 미식을 만났을 때","link":"javascript:;","retrieved":1640600647263,"image":"https://dive.hyundaicard.com/resources/images/upload/content/f477090f9bf74a8da8ae3789752a6821.jpg"},{"title":"해리네 집으로 놀러 오세요","contents":"Artist Inside: 해리 스타일스","link":"javascript:;","retrieved":1640600647263,"image":"https://dive.hyundaicard.com/resources/images/upload/content/80685bc5e6f34124a1c8a460e74102d8.jpg"},{"title":"지금, 아시아 아트 신","contents":"아트 바젤 홍콩 2022 리뷰","link":"javascript:;","retrieved":1640600647263,"image":"https://dive.hyundaicard.com/resources/images/upload/content/26ff35c4bf4d49f5a1dabe41374f4dbf.jpg"},{"title":"나의 바다야 나의 하늘아","contents":"6월의 현대카드 컬처 캘린더","link":"javascript:;","retrieved":1640600647263,"image":"https://dive.hyundaicard.com/resources/images/upload/content/9120bdcf04b3474dac57847148ae4281.jpg"},{"title":"해조의  재발견","contents":"바다 식물의 가능성을 시사하는 프로젝트 4","link":"javascript:;","retrieved":1640600647263,"image":"https://dive.hyundaicard.com/resources/images/upload/content/82462777434447ddac4f227708e17eab.jpg"},{"title":"위트와 조형  사이에서","contents":"산업디자인의 정수, 콘스탄틴 그리치치","link":"javascript:;","retrieved":1640600647263,"image":"https://dive.hyundaicard.com/resources/images/upload/content/7bc97357bbcc49d4a71292c13b0bb8b9.jpg"},{"title":"처음 만난  세계","contents":"NFT를 이끄는 아티스트들","link":"javascript:;","retrieved":1640600647263,"image":"https://dive.hyundaicard.com/resources/images/upload/content/831fbbda7c894850be3d090902f918d5.jpg"}]}