{"title":"현대카드 DIVE ─ POST","url":"https://dive.hyundaicard.com/web/post/post.hdc","favicon":"https://dive.hyundaicard.com/web/post/favicon.ico","elements":[{"title":"트래비스 스캇 첫 단독 내한 공연","contents":"현대카드 회원만을 위한 선예매 특권","link":"javascript:;","retrieved":1734006591155,"image":"https://dive.hyundaicard.com/resources/images/upload/content/ae597e384925482daa97420500cb63f6.jpg"},{"title":"이토록 달콤한 백화점","contents":"백화점 프리미엄 디저트 매장 5","link":"javascript:;","retrieved":1734006591155,"image":"https://dive.hyundaicard.com/resources/images/upload/content/c66509199e8940dba73c597f18f25e53.png"},{"title":"봄바람 로맨스","contents":"현대카드 라이브러리 4월의 새 책","link":"javascript:;","retrieved":1734006591155,"image":"https://dive.hyundaicard.com/resources/images/upload/content/fe13e1e8d04a472b9754d3ebcd2fd4ca.jpg"},{"title":"낭만과 열정 사이","contents":"뮤직 라이브러리 4월의 컬렉션","link":"javascript:;","retrieved":1734006591155,"image":"https://dive.hyundaicard.com/resources/images/upload/content/e343feb376a04722b1dabd8f12aa6dab.jpg"},{"title":"경계선을 넘나드는 사진가","contents":"4월의 디자이너, 다이안 아버스","link":"javascript:;","retrieved":1734006591155,"image":"https://dive.hyundaicard.com/resources/images/upload/content/2c2114d157a4425cb891cd5cfc52b6ee.jpg"},{"title":"크리에이터의 BGM","contents":"떠날 수 없는 SNS 피드를 만드는 곡 5","link":"javascript:;","retrieved":1734006591155,"image":"https://dive.hyundaicard.com/resources/images/upload/content/04060b5a207f41a3928291c3e4540cf6.png"},{"title":"도시의 숨은 보석","contents":"로컬 팔로잉 #2 이태원 추천 스폿","link":"javascript:;","retrieved":1734006591155,"image":"https://dive.hyundaicard.com/resources/images/upload/content/955a63a5897a41729ad0fab7b4475786.jpg"},{"title":"봄이 오면 그린","contents":"개성 넘치는 식물 관련 숍 추천 4","link":"javascript:;","retrieved":1734006591155,"image":"https://dive.hyundaicard.com/resources/images/upload/content/95147d0ddd3a4739a7fb05081b51275a.jpg"},{"title":"시공간을 초월하는 예술","contents":"현대카드 MoMA 디지털 월 아트 토크","link":"javascript:;","retrieved":1734006591155,"image":"https://dive.hyundaicard.com/resources/images/upload/content/f57853d868634fd1b0a7c8678b1ca83f.jpg"}]}